{
  "file": "output/strict_alive.yaml",
  "strict_alive_only": true,
  "test_rounds": 2,
  "require_success_rounds": 1,
  "strict_max_delay_ms": 8000,
  "proxy_count": 76,
  "best_ping_count": 1,
  "responsive_count": 1,
  "tcp_only_output_disabled": false,
  "names": [
    "RELAY-172.67.152.227-0151",
    "By EbraSha 8117",
    "https telegraph.rayan-config.workers.dev persian",
    "Channel id ShadowProxy66 SE",
    "oneclickvpnkeys US 1236",
    "oneclickvpnkeys FR",
    "oneclickvpnkeys US 6100",
    "oneclickvpnkeys XX",
    "oneclickvpnkeys XX 1477",
    "oneclickvpnkeys XX 3415",
    "oneclickvpnkeys US 6062",
    "oneclickvpnkeys XX 5969",
    "oneclickvpnkeys XX 6531",
    "oneclickvpnkeys US 5864",
    "oneclickvpnkeys US 2161",
    "oneclickvpnkeys US 3505",
    "v2ray1_ng US",
    "oneclickvpnkeys US 3874",
    "oneclickvpnkeys US 6424",
    "oneclickvpnkeys US 2966",
    "oneclickvpnkeys FR 6730",
    "oneclickvpnkeys FR 5195",
    "oneclickvpnkeys XX 5277",
    "configV2rayNG US 2357",
    "oneclickvpnkeys US 8890",
    "v2ray1_ng XX",
    "configV2rayForFree FI",
    "oneclickvpnkeys XX 8088",
    "oneclickvpnkeys XX 1385",
    "oneclickvpnkeys US 5338",
    "oneclickvpnkeys US 7986",
    "configV2rayNG US 7596",
    "oneclickvpnkeys XX 3995",
    "16 oneclickvpnkeys",
    "Zlinkid NL _MCI_iranc",
    "FreeConfigForYou",
    "chillguy_vpn 6446",
    "V2ConfigPro",
    "appsooner",
    "Tel- ProxyMtAlpha 4",
    "DE V2ngFast 2422",
    "IT RouTel1",
    "icv2ray",
    "Daily_Configs 7289",
    "Channel Daily_Configs 9182",
    "hope of freedom - anotherme_night",
    "filembad",
    "vmesskhodam",
    "CF EarnMoney_arz - 3",
    "vmesskhodam 6392",
    "TELEGRAM-vpnserverrr_vpnserverrr_vpnserverrr_vpnserverrr_vpnserverrr ed 512 News",
    "ProxyVPN11 - 5",
    "VLESS 4022",
    "65 NetFlowTools",
    "64 NetFlowTools",
    "64 oneclickvpnkeys",
    "hopev2ray 6673",
    "V2raySup0 1432",
    "EPODONIOS 9404",
    "oneclickvpnkeys JP",
    "oneclickvpnkeys US 6389",
    "oneclickvpnkeys US 3375",
    "ip_cf FR",
    "configV2rayNG FR",
    "oneclickvpnkeys FR 8889",
    "oneclickvpnkeys FR 1422",
    "oneclickvpnkeys NL 8785",
    "V2rayNG3 FR",
    "configshub2 PL",
    "AU",
    "SG",
    "SC SC- V2Ray_Hub1200",
    "KAFING_2 7085",
    "Maznet -SOS466",
    "AarazV2ray",
    "EPODONIOS 1800"
  ]
}