{
  "file": "output/lite.yaml",
  "proxy_count": 11,
  "top_country_count": 1,
  "top_global_count": 10,
  "responsive_count": 1,
  "lite_global_top_n": 10,
  "lite_max_total": 25,
  "combined_group_max": 30,
  "names": [
    "76 oneclickvpnkeys",
    "oneclickvpnkeys US 4863",
    "freenettir 3980",
    "https t.me QiangLieTuiJian 8259",
    "oneclickvpnkeys US 2347",
    "16 oneclickvpnkeys",
    "configV2rayNG US 7875",
    "hi_proxy_iran",
    "oneclickvpnkeys US 1700",
    "SG SG- VPNine1",
    "vpnserverrr VL-WS-N A XX 2ms 9338"
  ]
}