{
  "file": "output/lite.yaml",
  "proxy_count": 17,
  "top_country_count": 5,
  "top_global_count": 10,
  "responsive_count": 7,
  "lite_global_top_n": 10,
  "lite_max_total": 25,
  "combined_group_max": 30,
  "names": [
    "Channel id internet_azad_2026",
    "Channel id internet_azad_2026 2326",
    "Channel id internet_azad_2026 3436",
    "Channel id internet_azad_2026 5107",
    "Channel id internet_azad_2026 1022",
    "Channel id internet_azad_2026 1820",
    "Channel id internet_azad_2026 9157",
    "Arvand_soul Arvand_soul 1914",
    "Ap_Ir6 3238",
    "Arvand_soul Arvand_soul 5296",
    "ShadowsocksM US",
    "Channel id internet_azad_2026 CA 6858",
    "JP JP- VPNine1",
    "US Join Telegram Farah_VPN US",
    "SylphNet 2026-06-19 08 27",
    "v2rayNplus 4080",
    "EXPRESSVPN_420"
  ]
}