{
  "file": "output/lite.yaml",
  "proxy_count": 15,
  "top_country_count": 5,
  "top_global_count": 10,
  "responsive_count": 15,
  "lite_global_top_n": 10,
  "lite_max_total": 25,
  "combined_group_max": 30,
  "names": [
    "75 oneclickvpnkeys",
    "1 oneclickvpnkeys 3664",
    "30 oneclickvpnkeys",
    "oneclickvpnkeys US 5144",
    "v2configlab_ DE",
    "73 oneclickvpnkeys",
    "https telegraph.rayan-config.workers.dev persian",
    "https telegraph.rayan-config.workers.dev persian 5651",
    "v2ray_configs_pool US 5250",
    "hi_proxy_iran 7024",
    "NETMelliAnti",
    "oneclickvpnkeys US 8900",
    "34 oneclickvpnkeys",
    "79 oneclickvpnkeys",
    "filembad 6243"
  ]
}