{
  "generated_at": "2026-05-31T05:37:51+00:00",
  "manual_link_count": 8,
  "previous_output_available": true,
  "changed_file_count": 16,
  "files": [
    {
      "path": "output/SingBox/best-stable-safe.json",
      "exists": true,
      "previous_exists": true,
      "changed": true,
      "size": 15583,
      "sha256": "90179796a6f62b644d3e522b8fbc91b18444fc8dc98b4f30a511e8e71ea1e5c3",
      "previous_size": 15791,
      "previous_sha256": "4d6191f99734319713daecce32b044c08e4c2a0ca182497ca2c9d2bb608bfad1",
      "outbound_count": 28,
      "previous_outbound_count": 28,
      "added_outbounds": [
        "35 oneclickvpnkeys",
        "CF20",
        "configV2rayNG FR",
        "oneclickvpnkeys NL"
      ],
      "removed_outbounds": [
        "27 oneclickvpnkeys",
        "36 oneclickvpnkeys",
        "42 oneclickvpnkeys",
        "https telegraph.rayan-config.workers.dev persian"
      ]
    },
    {
      "path": "output/SingBox/import-ready.json",
      "exists": true,
      "previous_exists": true,
      "changed": true,
      "size": 16742,
      "sha256": "e730f6adc5c986a59ac11c3f684a749458ca9e30b5af69b90fb54c68bc7a828b",
      "previous_size": 16996,
      "previous_sha256": "2e39842220e710e0a50d078b69f2ebc2ee6d8a4524a91a4e87489ba5893ace7a",
      "outbound_count": 30,
      "previous_outbound_count": 30,
      "added_outbounds": [
        "35 oneclickvpnkeys",
        "CF20",
        "configV2rayNG FR",
        "oneclickvpnkeys NL"
      ],
      "removed_outbounds": [
        "27 oneclickvpnkeys",
        "36 oneclickvpnkeys",
        "42 oneclickvpnkeys",
        "https telegraph.rayan-config.workers.dev persian"
      ]
    },
    {
      "path": "output/SingBox/latest-safe.json",
      "exists": true,
      "previous_exists": true,
      "changed": true,
      "size": 15583,
      "sha256": "90179796a6f62b644d3e522b8fbc91b18444fc8dc98b4f30a511e8e71ea1e5c3",
      "previous_size": 15791,
      "previous_sha256": "4d6191f99734319713daecce32b044c08e4c2a0ca182497ca2c9d2bb608bfad1",
      "outbound_count": 28,
      "previous_outbound_count": 28,
      "added_outbounds": [
        "35 oneclickvpnkeys",
        "CF20",
        "configV2rayNG FR",
        "oneclickvpnkeys NL"
      ],
      "removed_outbounds": [
        "27 oneclickvpnkeys",
        "36 oneclickvpnkeys",
        "42 oneclickvpnkeys",
        "https telegraph.rayan-config.workers.dev persian"
      ]
    },
    {
      "path": "output/SingBox/lengkap-safe.json",
      "exists": true,
      "previous_exists": true,
      "changed": true,
      "size": 109878,
      "sha256": "a55d0d6dca16e85bbff066b75467d528bb097bee33d4232f9302b63e6ac303ac",
      "previous_size": 101487,
      "previous_sha256": "054ad6ebd33a9efdd77a436667ba4b3873ed2a085d92c01d9ce22ec5aa23da1c",
      "outbound_count": 172,
      "previous_outbound_count": 162,
      "added_outbounds": [
        "CA 39693 Telegram t.me SOSkeyNET",
        "CA 39709 Telegram t.me SOSkeyNET",
        "CA 39768 Telegram t.me SOSkeyNET",
        "CA 39775 Telegram t.me SOSkeyNET",
        "DE t.me Natrixo AA",
        "Fast Deploy Your Own Worker For Creation Of Configs https telegraph.rayan-config 9998",
        "FreakConfig FR",
        "FreeConffning",
        "GAME-01 2 DE av2ngFast",
        "GAME-02 CA 39768 Telegram t.me SOSkeyNET",
        "GAME-03 oneclickvpnkeys US 2740",
        "GAME-04 oneclickvpnkeys US 5770",
        "GAME-05 oneclickvpnkeys US 6157",
        "GAME-06 oneclickvpnkeys US 4616",
        "GAME-07 CA 39709 Telegram t.me SOSkeyNET",
        "GAME-08 CA 39775 Telegram t.me SOSkeyNET",
        "GAME-09 35 oneclickvpnkeys",
        "GAME-10 CF20",
        "GEN-01 2 DE av2ngFast",
        "GEN-02 CA 39768 Telegram t.me SOSkeyNET",
        "GEN-03 oneclickvpnkeys US 2740",
        "GEN-04 oneclickvpnkeys US 5770",
        "GEN-05 oneclickvpnkeys US 6157",
        "GEN-06 oneclickvpnkeys US 4616",
        "GEN-07 CA 39709 Telegram t.me SOSkeyNET",
        "GEN-08 CA 39775 Telegram t.me SOSkeyNET",
        "GEN-09 35 oneclickvpnkeys",
        "GEN-10 CF20",
        "GEN-11 oneclickvpnkeys US",
        "GEN-12 V2rayNG3 US",
        "GEN-13 oneclickvpnkeys US 4666",
        "GEN-14 oneclickvpnkeys US 5868",
        "GEN-15 oneclickvpnkeys US 6470",
        "ID-01 2 DE av2ngFast",
        "ID-02 CA 39768 Telegram t.me SOSkeyNET",
        "ID-03 oneclickvpnkeys US 2740",
        "ID-04 oneclickvpnkeys US 5770",
        "ID-05 oneclickvpnkeys US 6157",
        "ID-06 oneclickvpnkeys US 4616",
        "ID-07 CA 39709 Telegram t.me SOSkeyNET",
        "ID-08 CA 39775 Telegram t.me SOSkeyNET",
        "ID-09 35 oneclickvpnkeys",
        "ID-10 CF20",
        "ID-11 DE t.me Natrixo AA",
        "ID-12 LINK 10.lowh.net",
        "ID-13 LINK 15.lowh.net",
        "ID-14 LINK bel432 xl",
        "ID-15 LINK sg-trojan.1server.co",
        "ID-16 LINK VLESS-WS-TLS-443-apt50atpprem",
        "ID-17 LINK VMess-WS-TLS-443-akuku8",
        "KAFING_2 4061",
        "SOCIAL-01 2 DE av2ngFast",
        "SOCIAL-02 CA 39768 Telegram t.me SOSkeyNET",
        "SOCIAL-03 oneclickvpnkeys US 2740",
        "SOCIAL-04 oneclickvpnkeys US 5770",
        "SOCIAL-05 oneclickvpnkeys US 6157",
        "SOCIAL-06 oneclickvpnkeys US 4616",
        "SOCIAL-07 CA 39709 Telegram t.me SOSkeyNET",
        "SOCIAL-08 CA 39775 Telegram t.me SOSkeyNET",
        "SOCIAL-09 35 oneclickvpnkeys",
        "SOCIAL-10 CF20",
        "SOCIAL-11 https telegraph.rayan-config.workers.dev persian 6140",
        "SOCIAL-12 Fast Deploy Your Own Worker For Creation Of Configs https telegraph.rayan-config 9998",
        "SOCIAL-13 Fast Deploy Your Own Worker For Creation Of Configs https telegraph.rayan.dpdns",
        "SOCIAL-14 v2configlab",
        "SOCIAL-15 CA 39693 Telegram t.me SOSkeyNET",
        "STREAM-01 2 DE av2ngFast",
        "STREAM-02 CA 39768 Telegram t.me SOSkeyNET",
        "STREAM-03 oneclickvpnkeys US 2740",
        "STREAM-04 oneclickvpnkeys US 5770",
        "STREAM-05 oneclickvpnkeys US 6157",
        "STREAM-06 oneclickvpnkeys US 4616",
        "STREAM-07 CA 39709 Telegram t.me SOSkeyNET",
        "STREAM-08 CA 39775 Telegram t.me SOSkeyNET",
        "STREAM-09 35 oneclickvpnkeys",
        "STREAM-10 CF20",
        "URL-TEST TOP 10 INDONESIA",
        "US Join Telegram Farah_VPN US",
        "V2rayNG3 US",
        "WORK-01 2 DE av2ngFast",
        "WORK-02 CA 39768 Telegram t.me SOSkeyNET",
        "WORK-03 oneclickvpnkeys US 2740",
        "WORK-04 oneclickvpnkeys US 5770",
        "WORK-05 oneclickvpnkeys US 6157",
        "WORK-06 oneclickvpnkeys US 4616",
        "WORK-07 CA 39709 Telegram t.me SOSkeyNET",
        "WORK-08 CA 39775 Telegram t.me SOSkeyNET",
        "WORK-09 35 oneclickvpnkeys",
        "WORK-11 https telegraph.rayan-config.workers.dev persian 6140",
        "WORK-12 Fast Deploy Your Own Worker For Creation Of Configs https telegraph.rayan-config 9998",
        "WORK-13 Fast Deploy Your Own Worker For Creation Of Configs https telegraph.rayan.dpdns",
        "WORK-14 LINK 10.lowh.net",
        "WORK-15 LINK 15.lowh.net",
        "config_free2 2402",
        "config_free2 4595",
        "https telegraph.rayan-config.workers.dev persian 6140",
        "oneclickvpnkeys DE 7600",
        "oneclickvpnkeys US 2740",
        "oneclickvpnkeys US 3072",
        "oneclickvpnkeys US 3799"
      ],
      "removed_outbounds": [
        "26 oneclickvpnkeys",
        "27 oneclickvpnkeys",
        "36 oneclickvpnkeys",
        "42 oneclickvpnkeys",
        "76 oneclickvpnkeys",
        "79 oneclickvpnkeys",
        "90 oneclickvpnkeys",
        "By EbraSha 2179",
        "Fast Deploy Your Own Worker For Creation Of Configs https telegraph.rayan-config 6105",
        "GAME-01 27 oneclickvpnkeys",
        "GAME-02 v2configlab_ DE",
        "GAME-03 oneclickvpnkeys US 7975",
        "GAME-04 42 oneclickvpnkeys",
        "GAME-05 35 oneclickvpnkeys",
        "GAME-06 CF20",
        "GAME-07 HiByeVPNN",
        "GAME-08 telegram tajrobe_wiki",
        "GAME-09 configV2rayNG FR",
        "GAME-10 V2rayNG3 FR",
        "GEN-01 27 oneclickvpnkeys",
        "GEN-02 v2configlab_ DE",
        "GEN-03 oneclickvpnkeys US 7975",
        "GEN-04 42 oneclickvpnkeys",
        "GEN-05 35 oneclickvpnkeys",
        "GEN-06 Fast Deploy Your Own Worker For Creation Of Configs https telegraph.rayan.dpdns",
        "GEN-07 https telegraph.rayan.dpdns.org persian",
        "GEN-08 https telegraph.rayan-config.workers.dev persian",
        "GEN-09 https telegraph.rayan-config.workers.dev persian 9713",
        "GEN-10 Fast Deploy Your Own Worker For Creation Of Configs https telegraph.rayan-config 6105",
        "GEN-11 oneclickvpnkeys US 6784",
        "GEN-12 oneclickvpnkeys US 7902",
        "GEN-13 79 oneclickvpnkeys",
        "GEN-14 v2configlab",
        "GEN-15 2 DE av2ngFast",
        "ID-01 27 oneclickvpnkeys",
        "ID-02 v2configlab_ DE",
        "ID-03 oneclickvpnkeys US 7975",
        "ID-04 42 oneclickvpnkeys",
        "ID-05 35 oneclickvpnkeys",
        "ID-06 LINK 10.lowh.net",
        "ID-07 LINK 15.lowh.net",
        "ID-08 LINK bel432 xl",
        "ID-09 LINK sg-trojan.1server.co",
        "ID-10 LINK VLESS-WS-TLS-443-apt50atpprem",
        "ID-11 LINK VMess-WS-TLS-443-akuku8",
        "KAFING_2 4784",
        "ProxyEliteVPN",
        "RELAY-104.18.42.54-1541",
        "SOCIAL-01 27 oneclickvpnkeys",
        "SOCIAL-02 v2configlab_ DE",
        "SOCIAL-03 oneclickvpnkeys US 7975",
        "SOCIAL-04 42 oneclickvpnkeys",
        "SOCIAL-05 35 oneclickvpnkeys",
        "SOCIAL-06 Fast Deploy Your Own Worker For Creation Of Configs https telegraph.rayan.dpdns",
        "SOCIAL-07 https telegraph.rayan-config.workers.dev persian",
        "SOCIAL-08 https telegraph.rayan-config.workers.dev persian 9713",
        "SOCIAL-09 Fast Deploy Your Own Worker For Creation Of Configs https telegraph.rayan-config 6105",
        "SOCIAL-10 v2configlab",
        "SOCIAL-11 CF20",
        "SOCIAL-12 HiByeVPNN",
        "SOCIAL-13 telegram tajrobe_wiki",
        "SOCIAL-14 configV2rayNG FR",
        "SOCIAL-15 V2rayNG3 FR",
        "STREAM-01 27 oneclickvpnkeys",
        "STREAM-02 v2configlab_ DE",
        "STREAM-03 oneclickvpnkeys US 7975",
        "STREAM-04 42 oneclickvpnkeys",
        "STREAM-05 35 oneclickvpnkeys",
        "STREAM-06 CF20",
        "STREAM-07 HiByeVPNN",
        "STREAM-08 telegram tajrobe_wiki",
        "STREAM-09 configV2rayNG FR",
        "STREAM-10 V2rayNG3 FR",
        "URL-TEST TOP 5 INDONESIA",
        "V2rayNG3 FR",
        "VLESS",
        "WORK-01 27 oneclickvpnkeys",
        "WORK-02 v2configlab_ DE",
        "WORK-03 oneclickvpnkeys US 7975",
        "WORK-04 42 oneclickvpnkeys",
        "WORK-05 35 oneclickvpnkeys",
        "WORK-06 Fast Deploy Your Own Worker For Creation Of Configs https telegraph.rayan.dpdns",
        "WORK-07 https telegraph.rayan-config.workers.dev persian",
        "WORK-08 https telegraph.rayan-config.workers.dev persian 9713",
        "WORK-09 Fast Deploy Your Own Worker For Creation Of Configs https telegraph.rayan-config 6105",
        "WORK-11 HiByeVPNN",
        "WORK-12 telegram tajrobe_wiki",
        "WORK-13 configV2rayNG FR",
        "WORK-14 V2rayNG3 FR",
        "WORK-15 LINK 10.lowh.net",
        "chillguy_vpn",
        "config_free2 7235",
        "https telegraph.rayan-config.workers.dev persian",
        "https telegraph.rayan-config.workers.dev persian 9713",
        "oneclickvpnkeys DE 5963",
        "oneclickvpnkeys US 6784",
        "oneclickvpnkeys US 7902",
        "oneclickvpnkeys US 7975",
        "telegram tajrobe_wiki",
        "vpnbaz 9219"
      ]
    },
    {
      "path": "output/SingBox/mobile-stable-safe.json",
      "exists": true,
      "previous_exists": true,
      "changed": true,
      "size": 16341,
      "sha256": "1aef29ca779c996f5c8fbb261effa2ea0b20407766ba5e7a00779bc011f17e24",
      "previous_size": 16595,
      "previous_sha256": "ed3e4f091d702f288d3e7173d15e0d2639fe8cb6248385de74dd12efecf337bd",
      "outbound_count": 29,
      "previous_outbound_count": 29,
      "added_outbounds": [
        "35 oneclickvpnkeys",
        "CF20",
        "configV2rayNG FR",
        "oneclickvpnkeys NL"
      ],
      "removed_outbounds": [
        "27 oneclickvpnkeys",
        "36 oneclickvpnkeys",
        "42 oneclickvpnkeys",
        "https telegraph.rayan-config.workers.dev persian"
      ]
    },
    {
      "path": "output/fast.yaml",
      "exists": true,
      "previous_exists": true,
      "changed": true,
      "size": 53451,
      "sha256": "ef632c2e59d8b6804f0725e940e1177e92db45c0d5fe76bb1d1460231b691358",
      "previous_size": 48858,
      "previous_sha256": "f1f5f5bd4cec3c9cd9d3d6dd21567580c39333dbccac1aa23a9221622ae5b8e6",
      "proxy_count": 117,
      "previous_proxy_count": 107,
      "groups_count": 19,
      "previous_groups_count": 19,
      "rules_count": 67,
      "added_proxies": [
        "2 DE av2ngFast",
        "CA 39709 Telegram t.me SOSkeyNET",
        "CA 39768 Telegram t.me SOSkeyNET",
        "CA 39775 Telegram t.me SOSkeyNET",
        "FreakConfig FR",
        "GAME-01 2 DE av2ngFast",
        "GAME-02 CA 39768 Telegram t.me SOSkeyNET",
        "GAME-03 oneclickvpnkeys US 2740",
        "GAME-04 oneclickvpnkeys US 5770",
        "GAME-05 oneclickvpnkeys US 6157",
        "GAME-06 oneclickvpnkeys US 4616",
        "GAME-07 CA 39709 Telegram t.me SOSkeyNET",
        "GAME-08 CA 39775 Telegram t.me SOSkeyNET",
        "GAME-09 35 oneclickvpnkeys",
        "GAME-10 CF20",
        "GEN-01 2 DE av2ngFast",
        "GEN-02 CA 39768 Telegram t.me SOSkeyNET",
        "GEN-03 oneclickvpnkeys US 2740",
        "GEN-04 oneclickvpnkeys US 5770",
        "GEN-05 oneclickvpnkeys US 6157",
        "GEN-06 oneclickvpnkeys US 4616",
        "GEN-07 CA 39709 Telegram t.me SOSkeyNET",
        "GEN-08 CA 39775 Telegram t.me SOSkeyNET",
        "GEN-09 35 oneclickvpnkeys",
        "GEN-10 CF20",
        "GEN-11 oneclickvpnkeys DE",
        "GEN-12 oneclickvpnkeys DE 7600",
        "GEN-13 vpnbaz 7228",
        "GEN-14 v2ray1_ng FR",
        "GEN-15 configV2rayNG FR",
        "ID-01 2 DE av2ngFast",
        "ID-02 CA 39768 Telegram t.me SOSkeyNET",
        "ID-03 oneclickvpnkeys US 2740",
        "ID-04 oneclickvpnkeys US 5770",
        "ID-05 oneclickvpnkeys US 6157",
        "ID-06 oneclickvpnkeys US 4616",
        "ID-07 CA 39709 Telegram t.me SOSkeyNET",
        "ID-08 CA 39775 Telegram t.me SOSkeyNET",
        "ID-09 35 oneclickvpnkeys",
        "ID-10 CF20",
        "ID-11 LINK 10.lowh.net",
        "ID-12 LINK 15.lowh.net",
        "ID-13 LINK bel432 xl",
        "ID-14 LINK sg-trojan.1server.co",
        "ID-15 LINK VLESS-WS-TLS-443-apt50atpprem",
        "ID-16 LINK VMess-WS-TLS-443-akuku8",
        "SOCIAL-01 2 DE av2ngFast",
        "SOCIAL-02 CA 39768 Telegram t.me SOSkeyNET",
        "SOCIAL-03 oneclickvpnkeys US 2740",
        "SOCIAL-04 oneclickvpnkeys US 5770",
        "SOCIAL-05 oneclickvpnkeys US 6157",
        "SOCIAL-06 oneclickvpnkeys US 4616",
        "SOCIAL-07 CA 39709 Telegram t.me SOSkeyNET",
        "SOCIAL-08 CA 39775 Telegram t.me SOSkeyNET",
        "SOCIAL-09 35 oneclickvpnkeys",
        "SOCIAL-10 CF20",
        "SOCIAL-11 configV2rayNG FR",
        "SOCIAL-12 config_free2 2402",
        "SOCIAL-13 FreakConfig FR",
        "SOCIAL-14 config_free2 4595",
        "SOCIAL-15 LINK 10.lowh.net",
        "STREAM-01 2 DE av2ngFast",
        "STREAM-02 CA 39768 Telegram t.me SOSkeyNET",
        "STREAM-03 oneclickvpnkeys US 2740",
        "STREAM-04 oneclickvpnkeys US 5770",
        "STREAM-05 oneclickvpnkeys US 6157",
        "STREAM-06 oneclickvpnkeys US 4616",
        "STREAM-07 CA 39709 Telegram t.me SOSkeyNET",
        "STREAM-08 CA 39775 Telegram t.me SOSkeyNET",
        "STREAM-09 35 oneclickvpnkeys",
        "STREAM-10 CF20",
        "WORK-01 2 DE av2ngFast",
        "WORK-02 CA 39768 Telegram t.me SOSkeyNET",
        "WORK-03 oneclickvpnkeys US 2740",
        "WORK-04 oneclickvpnkeys US 5770",
        "WORK-05 oneclickvpnkeys US 6157",
        "WORK-06 oneclickvpnkeys US 4616",
        "WORK-07 CA 39709 Telegram t.me SOSkeyNET",
        "WORK-08 CA 39775 Telegram t.me SOSkeyNET",
        "WORK-09 35 oneclickvpnkeys",
        "WORK-10 CF20",
        "WORK-11 LINK 10.lowh.net",
        "WORK-12 LINK 15.lowh.net",
        "WORK-13 LINK bel432 xl",
        "WORK-14 LINK sg-trojan.1server.co",
        "WORK-15 LINK VLESS-WS-TLS-443-apt50atpprem",
        "config_free2 2402",
        "config_free2 4595",
        "oneclickvpnkeys DE",
        "oneclickvpnkeys DE 7600",
        "oneclickvpnkeys NL",
        "oneclickvpnkeys PL",
        "oneclickvpnkeys US 2740",
        "oneclickvpnkeys US 4616",
        "oneclickvpnkeys US 5770",
        "oneclickvpnkeys US 6157",
        "v2ray1_ng FR",
        "vpnbaz 7228"
      ],
      "removed_proxies": [
        "27 oneclickvpnkeys",
        "42 oneclickvpnkeys",
        "90 oneclickvpnkeys",
        "Fast Deploy Your Own Worker For Creation Of Configs https telegraph.rayan.dpdns",
        "GAME-01 27 oneclickvpnkeys",
        "GAME-02 v2configlab_ DE",
        "GAME-03 oneclickvpnkeys US 7975",
        "GAME-04 42 oneclickvpnkeys",
        "GAME-05 35 oneclickvpnkeys",
        "GAME-06 CF20",
        "GAME-07 HiByeVPNN",
        "GAME-08 telegram tajrobe_wiki",
        "GAME-09 configV2rayNG FR",
        "GAME-10 V2rayNG3 FR",
        "GEN-01 27 oneclickvpnkeys",
        "GEN-02 v2configlab_ DE",
        "GEN-03 oneclickvpnkeys US 7975",
        "GEN-04 42 oneclickvpnkeys",
        "GEN-05 35 oneclickvpnkeys",
        "GEN-06 Fast Deploy Your Own Worker For Creation Of Configs https telegraph.rayan.dpdns",
        "GEN-07 oneclickvpnkeys US 6784",
        "GEN-08 90 oneclickvpnkeys",
        "GEN-09 CF20",
        "GEN-10 HiByeVPNN",
        "GEN-11 telegram tajrobe_wiki",
        "GEN-12 configV2rayNG FR",
        "GEN-13 V2rayNG3 FR",
        "GEN-14 ProxyEliteVPN",
        "GEN-15 RELAY-104.18.42.54-1541",
        "HiByeVPNN",
        "ID-01 27 oneclickvpnkeys",
        "ID-02 v2configlab_ DE",
        "ID-03 oneclickvpnkeys US 7975",
        "ID-04 42 oneclickvpnkeys",
        "ID-05 35 oneclickvpnkeys",
        "ID-06 LINK 10.lowh.net",
        "ID-07 LINK 15.lowh.net",
        "ID-08 LINK bel432 xl",
        "ID-09 LINK sg-trojan.1server.co",
        "ID-10 LINK VLESS-WS-TLS-443-apt50atpprem",
        "ID-11 LINK VMess-WS-TLS-443-akuku8",
        "ProxyEliteVPN",
        "RELAY-104.18.42.54-1541",
        "SOCIAL-01 27 oneclickvpnkeys",
        "SOCIAL-02 v2configlab_ DE",
        "SOCIAL-03 oneclickvpnkeys US 7975",
        "SOCIAL-04 42 oneclickvpnkeys",
        "SOCIAL-05 35 oneclickvpnkeys",
        "SOCIAL-06 Fast Deploy Your Own Worker For Creation Of Configs https telegraph.rayan.dpdns",
        "SOCIAL-07 CF20",
        "SOCIAL-08 HiByeVPNN",
        "SOCIAL-09 telegram tajrobe_wiki",
        "SOCIAL-10 configV2rayNG FR",
        "SOCIAL-11 V2rayNG3 FR",
        "SOCIAL-12 LINK 10.lowh.net",
        "SOCIAL-13 LINK 15.lowh.net",
        "SOCIAL-14 LINK bel432 xl",
        "SOCIAL-15 LINK sg-trojan.1server.co",
        "STREAM-01 27 oneclickvpnkeys",
        "STREAM-02 v2configlab_ DE",
        "STREAM-03 oneclickvpnkeys US 7975",
        "STREAM-04 42 oneclickvpnkeys",
        "STREAM-05 35 oneclickvpnkeys",
        "STREAM-06 CF20",
        "STREAM-07 HiByeVPNN",
        "STREAM-08 telegram tajrobe_wiki",
        "STREAM-09 configV2rayNG FR",
        "STREAM-10 V2rayNG3 FR",
        "V2rayNG3 FR",
        "WORK-01 27 oneclickvpnkeys",
        "WORK-02 v2configlab_ DE",
        "WORK-03 oneclickvpnkeys US 7975",
        "WORK-04 42 oneclickvpnkeys",
        "WORK-05 35 oneclickvpnkeys",
        "WORK-06 Fast Deploy Your Own Worker For Creation Of Configs https telegraph.rayan.dpdns",
        "WORK-07 CF20",
        "WORK-08 HiByeVPNN",
        "WORK-09 telegram tajrobe_wiki",
        "WORK-10 configV2rayNG FR",
        "WORK-11 V2rayNG3 FR",
        "WORK-12 LINK 10.lowh.net",
        "WORK-13 LINK 15.lowh.net",
        "WORK-14 LINK bel432 xl",
        "WORK-15 LINK sg-trojan.1server.co",
        "oneclickvpnkeys US 6784",
        "oneclickvpnkeys US 7975",
        "telegram tajrobe_wiki",
        "v2configlab_ DE"
      ],
      "added_groups": [
        "URL-TEST TOP 10 INDONESIA"
      ],
      "removed_groups": [
        "URL-TEST TOP 5 INDONESIA"
      ]
    },
    {
      "path": "output/gaming.yaml",
      "exists": true,
      "previous_exists": true,
      "changed": true,
      "size": 38473,
      "sha256": "244289b215c4ad183a802d65ceac2a5ef568e7a1cb6d4a3faffc282f5c774c5e",
      "previous_size": 34960,
      "previous_sha256": "c52f122da7615d2828933b349ede1fa5c08c5aaa83df0fb56015f493717ae4e6",
      "proxy_count": 87,
      "previous_proxy_count": 82,
      "groups_count": 11,
      "previous_groups_count": 11,
      "rules_count": 67,
      "added_proxies": [
        "2 DE av2ngFast",
        "CA 39709 Telegram t.me SOSkeyNET",
        "CA 39768 Telegram t.me SOSkeyNET",
        "CA 39775 Telegram t.me SOSkeyNET",
        "GAME-01 2 DE av2ngFast",
        "GAME-02 CA 39768 Telegram t.me SOSkeyNET",
        "GAME-03 oneclickvpnkeys US 2740",
        "GAME-04 oneclickvpnkeys US 5770",
        "GAME-05 oneclickvpnkeys US 6157",
        "GAME-06 oneclickvpnkeys US 4616",
        "GAME-07 CA 39709 Telegram t.me SOSkeyNET",
        "GAME-08 CA 39775 Telegram t.me SOSkeyNET",
        "GAME-09 35 oneclickvpnkeys",
        "GAME-10 CF20",
        "GEN-01 2 DE av2ngFast",
        "GEN-02 CA 39768 Telegram t.me SOSkeyNET",
        "GEN-03 oneclickvpnkeys US 2740",
        "GEN-04 oneclickvpnkeys US 5770",
        "GEN-05 oneclickvpnkeys US 6157",
        "GEN-06 oneclickvpnkeys US 4616",
        "GEN-07 CA 39709 Telegram t.me SOSkeyNET",
        "GEN-08 CA 39775 Telegram t.me SOSkeyNET",
        "GEN-09 35 oneclickvpnkeys",
        "GEN-10 CF20",
        "ID-01 2 DE av2ngFast",
        "ID-02 CA 39768 Telegram t.me SOSkeyNET",
        "ID-03 oneclickvpnkeys US 2740",
        "ID-04 oneclickvpnkeys US 5770",
        "ID-05 oneclickvpnkeys US 6157",
        "ID-06 oneclickvpnkeys US 4616",
        "ID-07 CA 39709 Telegram t.me SOSkeyNET",
        "ID-08 CA 39775 Telegram t.me SOSkeyNET",
        "ID-09 35 oneclickvpnkeys",
        "ID-10 CF20",
        "ID-11 LINK bel432 xl",
        "SOCIAL-01 2 DE av2ngFast",
        "SOCIAL-02 CA 39768 Telegram t.me SOSkeyNET",
        "SOCIAL-03 oneclickvpnkeys US 2740",
        "SOCIAL-04 oneclickvpnkeys US 5770",
        "SOCIAL-05 oneclickvpnkeys US 6157",
        "SOCIAL-06 oneclickvpnkeys US 4616",
        "SOCIAL-07 CA 39709 Telegram t.me SOSkeyNET",
        "SOCIAL-08 CA 39775 Telegram t.me SOSkeyNET",
        "SOCIAL-09 35 oneclickvpnkeys",
        "SOCIAL-10 CF20",
        "STREAM-01 2 DE av2ngFast",
        "STREAM-02 CA 39768 Telegram t.me SOSkeyNET",
        "STREAM-03 oneclickvpnkeys US 2740",
        "STREAM-04 oneclickvpnkeys US 5770",
        "STREAM-05 oneclickvpnkeys US 6157",
        "STREAM-06 oneclickvpnkeys US 4616",
        "STREAM-07 CA 39709 Telegram t.me SOSkeyNET",
        "STREAM-08 CA 39775 Telegram t.me SOSkeyNET",
        "STREAM-09 35 oneclickvpnkeys",
        "STREAM-10 CF20",
        "WORK-01 2 DE av2ngFast",
        "WORK-02 CA 39768 Telegram t.me SOSkeyNET",
        "WORK-03 oneclickvpnkeys US 2740",
        "WORK-04 oneclickvpnkeys US 5770",
        "WORK-05 oneclickvpnkeys US 6157",
        "WORK-06 oneclickvpnkeys US 4616",
        "WORK-07 CA 39709 Telegram t.me SOSkeyNET",
        "WORK-08 CA 39775 Telegram t.me SOSkeyNET",
        "WORK-09 35 oneclickvpnkeys",
        "WORK-10 CF20",
        "oneclickvpnkeys US 2740",
        "oneclickvpnkeys US 4616",
        "oneclickvpnkeys US 5770",
        "oneclickvpnkeys US 6157"
      ],
      "removed_proxies": [
        "27 oneclickvpnkeys",
        "42 oneclickvpnkeys",
        "GAME-01 27 oneclickvpnkeys",
        "GAME-02 v2configlab_ DE",
        "GAME-03 oneclickvpnkeys US 7975",
        "GAME-04 42 oneclickvpnkeys",
        "GAME-05 35 oneclickvpnkeys",
        "GAME-06 CF20",
        "GAME-07 HiByeVPNN",
        "GAME-08 telegram tajrobe_wiki",
        "GAME-09 configV2rayNG FR",
        "GAME-10 V2rayNG3 FR",
        "GEN-01 27 oneclickvpnkeys",
        "GEN-02 v2configlab_ DE",
        "GEN-03 oneclickvpnkeys US 7975",
        "GEN-04 42 oneclickvpnkeys",
        "GEN-05 35 oneclickvpnkeys",
        "GEN-06 CF20",
        "GEN-07 HiByeVPNN",
        "GEN-08 telegram tajrobe_wiki",
        "GEN-09 configV2rayNG FR",
        "GEN-10 V2rayNG3 FR",
        "HiByeVPNN",
        "ID-01 27 oneclickvpnkeys",
        "ID-02 v2configlab_ DE",
        "ID-03 oneclickvpnkeys US 7975",
        "ID-04 42 oneclickvpnkeys",
        "ID-05 35 oneclickvpnkeys",
        "ID-06 LINK bel432 xl",
        "SOCIAL-01 27 oneclickvpnkeys",
        "SOCIAL-02 v2configlab_ DE",
        "SOCIAL-03 oneclickvpnkeys US 7975",
        "SOCIAL-04 42 oneclickvpnkeys",
        "SOCIAL-05 35 oneclickvpnkeys",
        "SOCIAL-06 CF20",
        "SOCIAL-07 HiByeVPNN",
        "SOCIAL-08 telegram tajrobe_wiki",
        "SOCIAL-09 configV2rayNG FR",
        "SOCIAL-10 V2rayNG3 FR",
        "STREAM-01 27 oneclickvpnkeys",
        "STREAM-02 v2configlab_ DE",
        "STREAM-03 oneclickvpnkeys US 7975",
        "STREAM-04 42 oneclickvpnkeys",
        "STREAM-05 35 oneclickvpnkeys",
        "STREAM-06 CF20",
        "STREAM-07 HiByeVPNN",
        "STREAM-08 telegram tajrobe_wiki",
        "STREAM-09 configV2rayNG FR",
        "STREAM-10 V2rayNG3 FR",
        "V2rayNG3 FR",
        "WORK-01 27 oneclickvpnkeys",
        "WORK-02 v2configlab_ DE",
        "WORK-03 oneclickvpnkeys US 7975",
        "WORK-04 42 oneclickvpnkeys",
        "WORK-05 35 oneclickvpnkeys",
        "WORK-06 CF20",
        "WORK-07 HiByeVPNN",
        "WORK-08 telegram tajrobe_wiki",
        "WORK-09 configV2rayNG FR",
        "WORK-10 V2rayNG3 FR",
        "configV2rayNG FR",
        "oneclickvpnkeys US 7975",
        "telegram tajrobe_wiki",
        "v2configlab_ DE"
      ],
      "added_groups": [],
      "removed_groups": []
    },
    {
      "path": "output/general.yaml",
      "exists": true,
      "previous_exists": true,
      "changed": true,
      "size": 36701,
      "sha256": "ca1e5712cd20aa3d6c27c90d204cd9394603478e0f2f15d8caff566c57090fda",
      "previous_size": 33188,
      "previous_sha256": "0518e927ce25628cb5b826fdbac94aaa1cfbe65d0ffe98cc886ad08e8c980d33",
      "proxy_count": 82,
      "previous_proxy_count": 77,
      "groups_count": 11,
      "previous_groups_count": 11,
      "rules_count": 67,
      "added_proxies": [
        "2 DE av2ngFast",
        "CA 39709 Telegram t.me SOSkeyNET",
        "CA 39768 Telegram t.me SOSkeyNET",
        "CA 39775 Telegram t.me SOSkeyNET",
        "GAME-01 2 DE av2ngFast",
        "GAME-02 CA 39768 Telegram t.me SOSkeyNET",
        "GAME-03 oneclickvpnkeys US 2740",
        "GAME-04 oneclickvpnkeys US 5770",
        "GAME-05 oneclickvpnkeys US 6157",
        "GAME-06 oneclickvpnkeys US 4616",
        "GAME-07 CA 39709 Telegram t.me SOSkeyNET",
        "GAME-08 CA 39775 Telegram t.me SOSkeyNET",
        "GAME-09 35 oneclickvpnkeys",
        "GAME-10 CF20",
        "GEN-01 2 DE av2ngFast",
        "GEN-02 CA 39768 Telegram t.me SOSkeyNET",
        "GEN-03 oneclickvpnkeys US 2740",
        "GEN-04 oneclickvpnkeys US 5770",
        "GEN-05 oneclickvpnkeys US 6157",
        "GEN-06 oneclickvpnkeys US 4616",
        "GEN-07 CA 39709 Telegram t.me SOSkeyNET",
        "GEN-08 CA 39775 Telegram t.me SOSkeyNET",
        "GEN-09 35 oneclickvpnkeys",
        "GEN-10 CF20",
        "ID-01 2 DE av2ngFast",
        "ID-02 CA 39768 Telegram t.me SOSkeyNET",
        "ID-03 oneclickvpnkeys US 2740",
        "ID-04 oneclickvpnkeys US 5770",
        "ID-05 oneclickvpnkeys US 6157",
        "ID-06 oneclickvpnkeys US 4616",
        "ID-07 CA 39709 Telegram t.me SOSkeyNET",
        "ID-08 CA 39775 Telegram t.me SOSkeyNET",
        "ID-09 35 oneclickvpnkeys",
        "ID-10 CF20",
        "ID-11 LINK bel432 xl",
        "SOCIAL-01 2 DE av2ngFast",
        "SOCIAL-02 CA 39768 Telegram t.me SOSkeyNET",
        "SOCIAL-03 oneclickvpnkeys US 2740",
        "SOCIAL-04 oneclickvpnkeys US 5770",
        "SOCIAL-05 oneclickvpnkeys US 6157",
        "SOCIAL-06 oneclickvpnkeys US 4616",
        "SOCIAL-07 CA 39709 Telegram t.me SOSkeyNET",
        "SOCIAL-08 CA 39775 Telegram t.me SOSkeyNET",
        "SOCIAL-09 35 oneclickvpnkeys",
        "SOCIAL-10 CF20",
        "STREAM-01 2 DE av2ngFast",
        "STREAM-02 CA 39768 Telegram t.me SOSkeyNET",
        "STREAM-03 oneclickvpnkeys US 2740",
        "STREAM-04 oneclickvpnkeys US 5770",
        "STREAM-05 oneclickvpnkeys US 6157",
        "STREAM-06 oneclickvpnkeys US 4616",
        "STREAM-07 CA 39709 Telegram t.me SOSkeyNET",
        "STREAM-08 CA 39775 Telegram t.me SOSkeyNET",
        "STREAM-09 35 oneclickvpnkeys",
        "STREAM-10 CF20",
        "WORK-01 2 DE av2ngFast",
        "WORK-02 CA 39768 Telegram t.me SOSkeyNET",
        "WORK-03 oneclickvpnkeys US 2740",
        "WORK-04 oneclickvpnkeys US 5770",
        "WORK-05 oneclickvpnkeys US 6157",
        "WORK-06 oneclickvpnkeys US 4616",
        "WORK-07 CA 39709 Telegram t.me SOSkeyNET",
        "WORK-08 CA 39775 Telegram t.me SOSkeyNET",
        "WORK-09 35 oneclickvpnkeys",
        "WORK-10 CF20",
        "oneclickvpnkeys US 2740",
        "oneclickvpnkeys US 4616",
        "oneclickvpnkeys US 5770",
        "oneclickvpnkeys US 6157"
      ],
      "removed_proxies": [
        "27 oneclickvpnkeys",
        "42 oneclickvpnkeys",
        "GAME-01 27 oneclickvpnkeys",
        "GAME-02 v2configlab_ DE",
        "GAME-03 oneclickvpnkeys US 7975",
        "GAME-04 42 oneclickvpnkeys",
        "GAME-05 35 oneclickvpnkeys",
        "GAME-06 CF20",
        "GAME-07 HiByeVPNN",
        "GAME-08 telegram tajrobe_wiki",
        "GAME-09 configV2rayNG FR",
        "GAME-10 V2rayNG3 FR",
        "GEN-01 27 oneclickvpnkeys",
        "GEN-02 v2configlab_ DE",
        "GEN-03 oneclickvpnkeys US 7975",
        "GEN-04 42 oneclickvpnkeys",
        "GEN-05 35 oneclickvpnkeys",
        "GEN-06 CF20",
        "GEN-07 HiByeVPNN",
        "GEN-08 telegram tajrobe_wiki",
        "GEN-09 configV2rayNG FR",
        "GEN-10 V2rayNG3 FR",
        "HiByeVPNN",
        "ID-01 27 oneclickvpnkeys",
        "ID-02 v2configlab_ DE",
        "ID-03 oneclickvpnkeys US 7975",
        "ID-04 42 oneclickvpnkeys",
        "ID-05 35 oneclickvpnkeys",
        "ID-06 LINK bel432 xl",
        "SOCIAL-01 27 oneclickvpnkeys",
        "SOCIAL-02 v2configlab_ DE",
        "SOCIAL-03 oneclickvpnkeys US 7975",
        "SOCIAL-04 42 oneclickvpnkeys",
        "SOCIAL-05 35 oneclickvpnkeys",
        "SOCIAL-06 CF20",
        "SOCIAL-07 HiByeVPNN",
        "SOCIAL-08 telegram tajrobe_wiki",
        "SOCIAL-09 configV2rayNG FR",
        "SOCIAL-10 V2rayNG3 FR",
        "STREAM-01 27 oneclickvpnkeys",
        "STREAM-02 v2configlab_ DE",
        "STREAM-03 oneclickvpnkeys US 7975",
        "STREAM-04 42 oneclickvpnkeys",
        "STREAM-05 35 oneclickvpnkeys",
        "STREAM-06 CF20",
        "STREAM-07 HiByeVPNN",
        "STREAM-08 telegram tajrobe_wiki",
        "STREAM-09 configV2rayNG FR",
        "STREAM-10 V2rayNG3 FR",
        "V2rayNG3 FR",
        "WORK-01 27 oneclickvpnkeys",
        "WORK-02 v2configlab_ DE",
        "WORK-03 oneclickvpnkeys US 7975",
        "WORK-04 42 oneclickvpnkeys",
        "WORK-05 35 oneclickvpnkeys",
        "WORK-06 CF20",
        "WORK-07 HiByeVPNN",
        "WORK-08 telegram tajrobe_wiki",
        "WORK-09 configV2rayNG FR",
        "WORK-10 V2rayNG3 FR",
        "configV2rayNG FR",
        "oneclickvpnkeys US 7975",
        "telegram tajrobe_wiki",
        "v2configlab_ DE"
      ],
      "added_groups": [],
      "removed_groups": []
    },
    {
      "path": "output/lengkap.yaml",
      "exists": true,
      "previous_exists": true,
      "changed": true,
      "size": 65319,
      "sha256": "747d45d3e7aa7daaef7b1f39fcf2380b285fd063cb75c4a7efcebb0bd221031e",
      "previous_size": 60012,
      "previous_sha256": "ee6d51f4fbd6f54cb894a331fb19c4b9c14cc6ee965c4d0ab62be238e18f372f",
      "proxy_count": 140,
      "previous_proxy_count": 130,
      "groups_count": 22,
      "previous_groups_count": 22,
      "rules_count": 67,
      "added_proxies": [
        "CA 39693 Telegram t.me SOSkeyNET",
        "CA 39709 Telegram t.me SOSkeyNET",
        "CA 39768 Telegram t.me SOSkeyNET",
        "CA 39775 Telegram t.me SOSkeyNET",
        "DE t.me Natrixo AA",
        "Fast Deploy Your Own Worker For Creation Of Configs https telegraph.rayan-config 9998",
        "FreakConfig FR",
        "FreeConffning",
        "GAME-01 2 DE av2ngFast",
        "GAME-02 CA 39768 Telegram t.me SOSkeyNET",
        "GAME-03 oneclickvpnkeys US 2740",
        "GAME-04 oneclickvpnkeys US 5770",
        "GAME-05 oneclickvpnkeys US 6157",
        "GAME-06 oneclickvpnkeys US 4616",
        "GAME-07 CA 39709 Telegram t.me SOSkeyNET",
        "GAME-08 CA 39775 Telegram t.me SOSkeyNET",
        "GAME-09 35 oneclickvpnkeys",
        "GAME-10 CF20",
        "GEN-01 2 DE av2ngFast",
        "GEN-02 CA 39768 Telegram t.me SOSkeyNET",
        "GEN-03 oneclickvpnkeys US 2740",
        "GEN-04 oneclickvpnkeys US 5770",
        "GEN-05 oneclickvpnkeys US 6157",
        "GEN-06 oneclickvpnkeys US 4616",
        "GEN-07 CA 39709 Telegram t.me SOSkeyNET",
        "GEN-08 CA 39775 Telegram t.me SOSkeyNET",
        "GEN-09 35 oneclickvpnkeys",
        "GEN-10 CF20",
        "GEN-11 oneclickvpnkeys US",
        "GEN-12 V2rayNG3 US",
        "GEN-13 oneclickvpnkeys US 4666",
        "GEN-14 oneclickvpnkeys US 5868",
        "GEN-15 oneclickvpnkeys US 6470",
        "ID-01 2 DE av2ngFast",
        "ID-02 CA 39768 Telegram t.me SOSkeyNET",
        "ID-03 oneclickvpnkeys US 2740",
        "ID-04 oneclickvpnkeys US 5770",
        "ID-05 oneclickvpnkeys US 6157",
        "ID-06 oneclickvpnkeys US 4616",
        "ID-07 CA 39709 Telegram t.me SOSkeyNET",
        "ID-08 CA 39775 Telegram t.me SOSkeyNET",
        "ID-09 35 oneclickvpnkeys",
        "ID-10 CF20",
        "ID-11 DE t.me Natrixo AA",
        "ID-12 LINK 10.lowh.net",
        "ID-13 LINK 15.lowh.net",
        "ID-14 LINK bel432 xl",
        "ID-15 LINK sg-trojan.1server.co",
        "ID-16 LINK VLESS-WS-TLS-443-apt50atpprem",
        "ID-17 LINK VMess-WS-TLS-443-akuku8",
        "KAFING_2 4061",
        "SOCIAL-01 2 DE av2ngFast",
        "SOCIAL-02 CA 39768 Telegram t.me SOSkeyNET",
        "SOCIAL-03 oneclickvpnkeys US 2740",
        "SOCIAL-04 oneclickvpnkeys US 5770",
        "SOCIAL-05 oneclickvpnkeys US 6157",
        "SOCIAL-06 oneclickvpnkeys US 4616",
        "SOCIAL-07 CA 39709 Telegram t.me SOSkeyNET",
        "SOCIAL-08 CA 39775 Telegram t.me SOSkeyNET",
        "SOCIAL-09 35 oneclickvpnkeys",
        "SOCIAL-10 CF20",
        "SOCIAL-11 https telegraph.rayan-config.workers.dev persian 6140",
        "SOCIAL-12 Fast Deploy Your Own Worker For Creation Of Configs https telegraph.rayan-config 9998",
        "SOCIAL-13 Fast Deploy Your Own Worker For Creation Of Configs https telegraph.rayan.dpdns",
        "SOCIAL-14 v2configlab",
        "SOCIAL-15 CA 39693 Telegram t.me SOSkeyNET",
        "STREAM-01 2 DE av2ngFast",
        "STREAM-02 CA 39768 Telegram t.me SOSkeyNET",
        "STREAM-03 oneclickvpnkeys US 2740",
        "STREAM-04 oneclickvpnkeys US 5770",
        "STREAM-05 oneclickvpnkeys US 6157",
        "STREAM-06 oneclickvpnkeys US 4616",
        "STREAM-07 CA 39709 Telegram t.me SOSkeyNET",
        "STREAM-08 CA 39775 Telegram t.me SOSkeyNET",
        "STREAM-09 35 oneclickvpnkeys",
        "STREAM-10 CF20",
        "US Join Telegram Farah_VPN US",
        "V2rayNG3 US",
        "WORK-01 2 DE av2ngFast",
        "WORK-02 CA 39768 Telegram t.me SOSkeyNET",
        "WORK-03 oneclickvpnkeys US 2740",
        "WORK-04 oneclickvpnkeys US 5770",
        "WORK-05 oneclickvpnkeys US 6157",
        "WORK-06 oneclickvpnkeys US 4616",
        "WORK-07 CA 39709 Telegram t.me SOSkeyNET",
        "WORK-08 CA 39775 Telegram t.me SOSkeyNET",
        "WORK-09 35 oneclickvpnkeys",
        "WORK-11 https telegraph.rayan-config.workers.dev persian 6140",
        "WORK-12 Fast Deploy Your Own Worker For Creation Of Configs https telegraph.rayan-config 9998",
        "WORK-13 Fast Deploy Your Own Worker For Creation Of Configs https telegraph.rayan.dpdns",
        "WORK-14 LINK 10.lowh.net",
        "WORK-15 LINK 15.lowh.net",
        "config_free2 2402",
        "config_free2 4595",
        "https telegraph.rayan-config.workers.dev persian 6140",
        "oneclickvpnkeys DE 7600",
        "oneclickvpnkeys US 2740",
        "oneclickvpnkeys US 3072",
        "oneclickvpnkeys US 3799",
        "oneclickvpnkeys US 4616"
      ],
      "removed_proxies": [
        "26 oneclickvpnkeys",
        "27 oneclickvpnkeys",
        "36 oneclickvpnkeys",
        "42 oneclickvpnkeys",
        "76 oneclickvpnkeys",
        "79 oneclickvpnkeys",
        "90 oneclickvpnkeys",
        "By EbraSha 2179",
        "Fast Deploy Your Own Worker For Creation Of Configs https telegraph.rayan-config 6105",
        "GAME-01 27 oneclickvpnkeys",
        "GAME-02 v2configlab_ DE",
        "GAME-03 oneclickvpnkeys US 7975",
        "GAME-04 42 oneclickvpnkeys",
        "GAME-05 35 oneclickvpnkeys",
        "GAME-06 CF20",
        "GAME-07 HiByeVPNN",
        "GAME-08 telegram tajrobe_wiki",
        "GAME-09 configV2rayNG FR",
        "GAME-10 V2rayNG3 FR",
        "GEN-01 27 oneclickvpnkeys",
        "GEN-02 v2configlab_ DE",
        "GEN-03 oneclickvpnkeys US 7975",
        "GEN-04 42 oneclickvpnkeys",
        "GEN-05 35 oneclickvpnkeys",
        "GEN-06 Fast Deploy Your Own Worker For Creation Of Configs https telegraph.rayan.dpdns",
        "GEN-07 https telegraph.rayan.dpdns.org persian",
        "GEN-08 https telegraph.rayan-config.workers.dev persian",
        "GEN-09 https telegraph.rayan-config.workers.dev persian 9713",
        "GEN-10 Fast Deploy Your Own Worker For Creation Of Configs https telegraph.rayan-config 6105",
        "GEN-11 oneclickvpnkeys US 6784",
        "GEN-12 oneclickvpnkeys US 7902",
        "GEN-13 79 oneclickvpnkeys",
        "GEN-14 v2configlab",
        "GEN-15 2 DE av2ngFast",
        "ID-01 27 oneclickvpnkeys",
        "ID-02 v2configlab_ DE",
        "ID-03 oneclickvpnkeys US 7975",
        "ID-04 42 oneclickvpnkeys",
        "ID-05 35 oneclickvpnkeys",
        "ID-06 LINK 10.lowh.net",
        "ID-07 LINK 15.lowh.net",
        "ID-08 LINK bel432 xl",
        "ID-09 LINK sg-trojan.1server.co",
        "ID-10 LINK VLESS-WS-TLS-443-apt50atpprem",
        "ID-11 LINK VMess-WS-TLS-443-akuku8",
        "KAFING_2 4784",
        "ProxyEliteVPN",
        "RELAY-104.18.42.54-1541",
        "SOCIAL-01 27 oneclickvpnkeys",
        "SOCIAL-02 v2configlab_ DE",
        "SOCIAL-03 oneclickvpnkeys US 7975",
        "SOCIAL-04 42 oneclickvpnkeys",
        "SOCIAL-05 35 oneclickvpnkeys",
        "SOCIAL-06 Fast Deploy Your Own Worker For Creation Of Configs https telegraph.rayan.dpdns",
        "SOCIAL-07 https telegraph.rayan-config.workers.dev persian",
        "SOCIAL-08 https telegraph.rayan-config.workers.dev persian 9713",
        "SOCIAL-09 Fast Deploy Your Own Worker For Creation Of Configs https telegraph.rayan-config 6105",
        "SOCIAL-10 v2configlab",
        "SOCIAL-11 CF20",
        "SOCIAL-12 HiByeVPNN",
        "SOCIAL-13 telegram tajrobe_wiki",
        "SOCIAL-14 configV2rayNG FR",
        "SOCIAL-15 V2rayNG3 FR",
        "STREAM-01 27 oneclickvpnkeys",
        "STREAM-02 v2configlab_ DE",
        "STREAM-03 oneclickvpnkeys US 7975",
        "STREAM-04 42 oneclickvpnkeys",
        "STREAM-05 35 oneclickvpnkeys",
        "STREAM-06 CF20",
        "STREAM-07 HiByeVPNN",
        "STREAM-08 telegram tajrobe_wiki",
        "STREAM-09 configV2rayNG FR",
        "STREAM-10 V2rayNG3 FR",
        "V2rayNG3 FR",
        "VLESS",
        "WORK-01 27 oneclickvpnkeys",
        "WORK-02 v2configlab_ DE",
        "WORK-03 oneclickvpnkeys US 7975",
        "WORK-04 42 oneclickvpnkeys",
        "WORK-05 35 oneclickvpnkeys",
        "WORK-06 Fast Deploy Your Own Worker For Creation Of Configs https telegraph.rayan.dpdns",
        "WORK-07 https telegraph.rayan-config.workers.dev persian",
        "WORK-08 https telegraph.rayan-config.workers.dev persian 9713",
        "WORK-09 Fast Deploy Your Own Worker For Creation Of Configs https telegraph.rayan-config 6105",
        "WORK-11 HiByeVPNN",
        "WORK-12 telegram tajrobe_wiki",
        "WORK-13 configV2rayNG FR",
        "WORK-14 V2rayNG3 FR",
        "WORK-15 LINK 10.lowh.net",
        "chillguy_vpn",
        "config_free2 7235",
        "https telegraph.rayan-config.workers.dev persian",
        "https telegraph.rayan-config.workers.dev persian 9713",
        "oneclickvpnkeys DE 5963",
        "oneclickvpnkeys US 6784",
        "oneclickvpnkeys US 7902",
        "oneclickvpnkeys US 7975",
        "telegram tajrobe_wiki",
        "vpnbaz 9219"
      ],
      "added_groups": [
        "URL-TEST TOP 10 INDONESIA"
      ],
      "removed_groups": [
        "URL-TEST TOP 5 INDONESIA"
      ]
    },
    {
      "path": "output/lengkap_alive.yaml",
      "exists": true,
      "previous_exists": true,
      "changed": true,
      "size": 65319,
      "sha256": "747d45d3e7aa7daaef7b1f39fcf2380b285fd063cb75c4a7efcebb0bd221031e",
      "previous_size": 60012,
      "previous_sha256": "ee6d51f4fbd6f54cb894a331fb19c4b9c14cc6ee965c4d0ab62be238e18f372f",
      "proxy_count": 140,
      "previous_proxy_count": 130,
      "groups_count": 22,
      "previous_groups_count": 22,
      "rules_count": 67,
      "added_proxies": [
        "CA 39693 Telegram t.me SOSkeyNET",
        "CA 39709 Telegram t.me SOSkeyNET",
        "CA 39768 Telegram t.me SOSkeyNET",
        "CA 39775 Telegram t.me SOSkeyNET",
        "DE t.me Natrixo AA",
        "Fast Deploy Your Own Worker For Creation Of Configs https telegraph.rayan-config 9998",
        "FreakConfig FR",
        "FreeConffning",
        "GAME-01 2 DE av2ngFast",
        "GAME-02 CA 39768 Telegram t.me SOSkeyNET",
        "GAME-03 oneclickvpnkeys US 2740",
        "GAME-04 oneclickvpnkeys US 5770",
        "GAME-05 oneclickvpnkeys US 6157",
        "GAME-06 oneclickvpnkeys US 4616",
        "GAME-07 CA 39709 Telegram t.me SOSkeyNET",
        "GAME-08 CA 39775 Telegram t.me SOSkeyNET",
        "GAME-09 35 oneclickvpnkeys",
        "GAME-10 CF20",
        "GEN-01 2 DE av2ngFast",
        "GEN-02 CA 39768 Telegram t.me SOSkeyNET",
        "GEN-03 oneclickvpnkeys US 2740",
        "GEN-04 oneclickvpnkeys US 5770",
        "GEN-05 oneclickvpnkeys US 6157",
        "GEN-06 oneclickvpnkeys US 4616",
        "GEN-07 CA 39709 Telegram t.me SOSkeyNET",
        "GEN-08 CA 39775 Telegram t.me SOSkeyNET",
        "GEN-09 35 oneclickvpnkeys",
        "GEN-10 CF20",
        "GEN-11 oneclickvpnkeys US",
        "GEN-12 V2rayNG3 US",
        "GEN-13 oneclickvpnkeys US 4666",
        "GEN-14 oneclickvpnkeys US 5868",
        "GEN-15 oneclickvpnkeys US 6470",
        "ID-01 2 DE av2ngFast",
        "ID-02 CA 39768 Telegram t.me SOSkeyNET",
        "ID-03 oneclickvpnkeys US 2740",
        "ID-04 oneclickvpnkeys US 5770",
        "ID-05 oneclickvpnkeys US 6157",
        "ID-06 oneclickvpnkeys US 4616",
        "ID-07 CA 39709 Telegram t.me SOSkeyNET",
        "ID-08 CA 39775 Telegram t.me SOSkeyNET",
        "ID-09 35 oneclickvpnkeys",
        "ID-10 CF20",
        "ID-11 DE t.me Natrixo AA",
        "ID-12 LINK 10.lowh.net",
        "ID-13 LINK 15.lowh.net",
        "ID-14 LINK bel432 xl",
        "ID-15 LINK sg-trojan.1server.co",
        "ID-16 LINK VLESS-WS-TLS-443-apt50atpprem",
        "ID-17 LINK VMess-WS-TLS-443-akuku8",
        "KAFING_2 4061",
        "SOCIAL-01 2 DE av2ngFast",
        "SOCIAL-02 CA 39768 Telegram t.me SOSkeyNET",
        "SOCIAL-03 oneclickvpnkeys US 2740",
        "SOCIAL-04 oneclickvpnkeys US 5770",
        "SOCIAL-05 oneclickvpnkeys US 6157",
        "SOCIAL-06 oneclickvpnkeys US 4616",
        "SOCIAL-07 CA 39709 Telegram t.me SOSkeyNET",
        "SOCIAL-08 CA 39775 Telegram t.me SOSkeyNET",
        "SOCIAL-09 35 oneclickvpnkeys",
        "SOCIAL-10 CF20",
        "SOCIAL-11 https telegraph.rayan-config.workers.dev persian 6140",
        "SOCIAL-12 Fast Deploy Your Own Worker For Creation Of Configs https telegraph.rayan-config 9998",
        "SOCIAL-13 Fast Deploy Your Own Worker For Creation Of Configs https telegraph.rayan.dpdns",
        "SOCIAL-14 v2configlab",
        "SOCIAL-15 CA 39693 Telegram t.me SOSkeyNET",
        "STREAM-01 2 DE av2ngFast",
        "STREAM-02 CA 39768 Telegram t.me SOSkeyNET",
        "STREAM-03 oneclickvpnkeys US 2740",
        "STREAM-04 oneclickvpnkeys US 5770",
        "STREAM-05 oneclickvpnkeys US 6157",
        "STREAM-06 oneclickvpnkeys US 4616",
        "STREAM-07 CA 39709 Telegram t.me SOSkeyNET",
        "STREAM-08 CA 39775 Telegram t.me SOSkeyNET",
        "STREAM-09 35 oneclickvpnkeys",
        "STREAM-10 CF20",
        "US Join Telegram Farah_VPN US",
        "V2rayNG3 US",
        "WORK-01 2 DE av2ngFast",
        "WORK-02 CA 39768 Telegram t.me SOSkeyNET",
        "WORK-03 oneclickvpnkeys US 2740",
        "WORK-04 oneclickvpnkeys US 5770",
        "WORK-05 oneclickvpnkeys US 6157",
        "WORK-06 oneclickvpnkeys US 4616",
        "WORK-07 CA 39709 Telegram t.me SOSkeyNET",
        "WORK-08 CA 39775 Telegram t.me SOSkeyNET",
        "WORK-09 35 oneclickvpnkeys",
        "WORK-11 https telegraph.rayan-config.workers.dev persian 6140",
        "WORK-12 Fast Deploy Your Own Worker For Creation Of Configs https telegraph.rayan-config 9998",
        "WORK-13 Fast Deploy Your Own Worker For Creation Of Configs https telegraph.rayan.dpdns",
        "WORK-14 LINK 10.lowh.net",
        "WORK-15 LINK 15.lowh.net",
        "config_free2 2402",
        "config_free2 4595",
        "https telegraph.rayan-config.workers.dev persian 6140",
        "oneclickvpnkeys DE 7600",
        "oneclickvpnkeys US 2740",
        "oneclickvpnkeys US 3072",
        "oneclickvpnkeys US 3799",
        "oneclickvpnkeys US 4616"
      ],
      "removed_proxies": [
        "26 oneclickvpnkeys",
        "27 oneclickvpnkeys",
        "36 oneclickvpnkeys",
        "42 oneclickvpnkeys",
        "76 oneclickvpnkeys",
        "79 oneclickvpnkeys",
        "90 oneclickvpnkeys",
        "By EbraSha 2179",
        "Fast Deploy Your Own Worker For Creation Of Configs https telegraph.rayan-config 6105",
        "GAME-01 27 oneclickvpnkeys",
        "GAME-02 v2configlab_ DE",
        "GAME-03 oneclickvpnkeys US 7975",
        "GAME-04 42 oneclickvpnkeys",
        "GAME-05 35 oneclickvpnkeys",
        "GAME-06 CF20",
        "GAME-07 HiByeVPNN",
        "GAME-08 telegram tajrobe_wiki",
        "GAME-09 configV2rayNG FR",
        "GAME-10 V2rayNG3 FR",
        "GEN-01 27 oneclickvpnkeys",
        "GEN-02 v2configlab_ DE",
        "GEN-03 oneclickvpnkeys US 7975",
        "GEN-04 42 oneclickvpnkeys",
        "GEN-05 35 oneclickvpnkeys",
        "GEN-06 Fast Deploy Your Own Worker For Creation Of Configs https telegraph.rayan.dpdns",
        "GEN-07 https telegraph.rayan.dpdns.org persian",
        "GEN-08 https telegraph.rayan-config.workers.dev persian",
        "GEN-09 https telegraph.rayan-config.workers.dev persian 9713",
        "GEN-10 Fast Deploy Your Own Worker For Creation Of Configs https telegraph.rayan-config 6105",
        "GEN-11 oneclickvpnkeys US 6784",
        "GEN-12 oneclickvpnkeys US 7902",
        "GEN-13 79 oneclickvpnkeys",
        "GEN-14 v2configlab",
        "GEN-15 2 DE av2ngFast",
        "ID-01 27 oneclickvpnkeys",
        "ID-02 v2configlab_ DE",
        "ID-03 oneclickvpnkeys US 7975",
        "ID-04 42 oneclickvpnkeys",
        "ID-05 35 oneclickvpnkeys",
        "ID-06 LINK 10.lowh.net",
        "ID-07 LINK 15.lowh.net",
        "ID-08 LINK bel432 xl",
        "ID-09 LINK sg-trojan.1server.co",
        "ID-10 LINK VLESS-WS-TLS-443-apt50atpprem",
        "ID-11 LINK VMess-WS-TLS-443-akuku8",
        "KAFING_2 4784",
        "ProxyEliteVPN",
        "RELAY-104.18.42.54-1541",
        "SOCIAL-01 27 oneclickvpnkeys",
        "SOCIAL-02 v2configlab_ DE",
        "SOCIAL-03 oneclickvpnkeys US 7975",
        "SOCIAL-04 42 oneclickvpnkeys",
        "SOCIAL-05 35 oneclickvpnkeys",
        "SOCIAL-06 Fast Deploy Your Own Worker For Creation Of Configs https telegraph.rayan.dpdns",
        "SOCIAL-07 https telegraph.rayan-config.workers.dev persian",
        "SOCIAL-08 https telegraph.rayan-config.workers.dev persian 9713",
        "SOCIAL-09 Fast Deploy Your Own Worker For Creation Of Configs https telegraph.rayan-config 6105",
        "SOCIAL-10 v2configlab",
        "SOCIAL-11 CF20",
        "SOCIAL-12 HiByeVPNN",
        "SOCIAL-13 telegram tajrobe_wiki",
        "SOCIAL-14 configV2rayNG FR",
        "SOCIAL-15 V2rayNG3 FR",
        "STREAM-01 27 oneclickvpnkeys",
        "STREAM-02 v2configlab_ DE",
        "STREAM-03 oneclickvpnkeys US 7975",
        "STREAM-04 42 oneclickvpnkeys",
        "STREAM-05 35 oneclickvpnkeys",
        "STREAM-06 CF20",
        "STREAM-07 HiByeVPNN",
        "STREAM-08 telegram tajrobe_wiki",
        "STREAM-09 configV2rayNG FR",
        "STREAM-10 V2rayNG3 FR",
        "V2rayNG3 FR",
        "VLESS",
        "WORK-01 27 oneclickvpnkeys",
        "WORK-02 v2configlab_ DE",
        "WORK-03 oneclickvpnkeys US 7975",
        "WORK-04 42 oneclickvpnkeys",
        "WORK-05 35 oneclickvpnkeys",
        "WORK-06 Fast Deploy Your Own Worker For Creation Of Configs https telegraph.rayan.dpdns",
        "WORK-07 https telegraph.rayan-config.workers.dev persian",
        "WORK-08 https telegraph.rayan-config.workers.dev persian 9713",
        "WORK-09 Fast Deploy Your Own Worker For Creation Of Configs https telegraph.rayan-config 6105",
        "WORK-11 HiByeVPNN",
        "WORK-12 telegram tajrobe_wiki",
        "WORK-13 configV2rayNG FR",
        "WORK-14 V2rayNG3 FR",
        "WORK-15 LINK 10.lowh.net",
        "chillguy_vpn",
        "config_free2 7235",
        "https telegraph.rayan-config.workers.dev persian",
        "https telegraph.rayan-config.workers.dev persian 9713",
        "oneclickvpnkeys DE 5963",
        "oneclickvpnkeys US 6784",
        "oneclickvpnkeys US 7902",
        "oneclickvpnkeys US 7975",
        "telegram tajrobe_wiki",
        "vpnbaz 9219"
      ],
      "added_groups": [
        "URL-TEST TOP 10 INDONESIA"
      ],
      "removed_groups": [
        "URL-TEST TOP 5 INDONESIA"
      ]
    },
    {
      "path": "output/lite.yaml",
      "exists": true,
      "previous_exists": true,
      "changed": true,
      "size": 54056,
      "sha256": "d607a219ca1b3db32f1cfd66f0f868ffde8aaab69b8a9a63d43ad0f4138b38d3",
      "previous_size": 49392,
      "previous_sha256": "164230aaf645f9e95a379d6f59dbb4d10f353f8e6d4ae14e5f7826e9da35acc9",
      "proxy_count": 117,
      "previous_proxy_count": 107,
      "groups_count": 20,
      "previous_groups_count": 20,
      "rules_count": 67,
      "added_proxies": [
        "2 DE av2ngFast",
        "CA 39709 Telegram t.me SOSkeyNET",
        "CA 39768 Telegram t.me SOSkeyNET",
        "CA 39775 Telegram t.me SOSkeyNET",
        "FreakConfig FR",
        "GAME-01 2 DE av2ngFast",
        "GAME-02 CA 39768 Telegram t.me SOSkeyNET",
        "GAME-03 oneclickvpnkeys US 2740",
        "GAME-04 oneclickvpnkeys US 5770",
        "GAME-05 oneclickvpnkeys US 6157",
        "GAME-06 oneclickvpnkeys US 4616",
        "GAME-07 CA 39709 Telegram t.me SOSkeyNET",
        "GAME-08 CA 39775 Telegram t.me SOSkeyNET",
        "GAME-09 35 oneclickvpnkeys",
        "GAME-10 CF20",
        "GEN-01 2 DE av2ngFast",
        "GEN-02 CA 39768 Telegram t.me SOSkeyNET",
        "GEN-03 oneclickvpnkeys US 2740",
        "GEN-04 oneclickvpnkeys US 5770",
        "GEN-05 oneclickvpnkeys US 6157",
        "GEN-06 oneclickvpnkeys US 4616",
        "GEN-07 CA 39709 Telegram t.me SOSkeyNET",
        "GEN-08 CA 39775 Telegram t.me SOSkeyNET",
        "GEN-09 35 oneclickvpnkeys",
        "GEN-10 CF20",
        "GEN-11 oneclickvpnkeys DE",
        "GEN-12 oneclickvpnkeys DE 7600",
        "GEN-13 vpnbaz 7228",
        "GEN-14 v2ray1_ng FR",
        "GEN-15 configV2rayNG FR",
        "ID-01 2 DE av2ngFast",
        "ID-02 CA 39768 Telegram t.me SOSkeyNET",
        "ID-03 oneclickvpnkeys US 2740",
        "ID-04 oneclickvpnkeys US 5770",
        "ID-05 oneclickvpnkeys US 6157",
        "ID-06 oneclickvpnkeys US 4616",
        "ID-07 CA 39709 Telegram t.me SOSkeyNET",
        "ID-08 CA 39775 Telegram t.me SOSkeyNET",
        "ID-09 35 oneclickvpnkeys",
        "ID-10 CF20",
        "ID-11 LINK 10.lowh.net",
        "ID-12 LINK 15.lowh.net",
        "ID-13 LINK bel432 xl",
        "ID-14 LINK sg-trojan.1server.co",
        "ID-15 LINK VLESS-WS-TLS-443-apt50atpprem",
        "ID-16 LINK VMess-WS-TLS-443-akuku8",
        "SOCIAL-01 2 DE av2ngFast",
        "SOCIAL-02 CA 39768 Telegram t.me SOSkeyNET",
        "SOCIAL-03 oneclickvpnkeys US 2740",
        "SOCIAL-04 oneclickvpnkeys US 5770",
        "SOCIAL-05 oneclickvpnkeys US 6157",
        "SOCIAL-06 oneclickvpnkeys US 4616",
        "SOCIAL-07 CA 39709 Telegram t.me SOSkeyNET",
        "SOCIAL-08 CA 39775 Telegram t.me SOSkeyNET",
        "SOCIAL-09 35 oneclickvpnkeys",
        "SOCIAL-10 CF20",
        "SOCIAL-11 configV2rayNG FR",
        "SOCIAL-12 config_free2 2402",
        "SOCIAL-13 FreakConfig FR",
        "SOCIAL-14 config_free2 4595",
        "SOCIAL-15 LINK 10.lowh.net",
        "STREAM-01 2 DE av2ngFast",
        "STREAM-02 CA 39768 Telegram t.me SOSkeyNET",
        "STREAM-03 oneclickvpnkeys US 2740",
        "STREAM-04 oneclickvpnkeys US 5770",
        "STREAM-05 oneclickvpnkeys US 6157",
        "STREAM-06 oneclickvpnkeys US 4616",
        "STREAM-07 CA 39709 Telegram t.me SOSkeyNET",
        "STREAM-08 CA 39775 Telegram t.me SOSkeyNET",
        "STREAM-09 35 oneclickvpnkeys",
        "STREAM-10 CF20",
        "WORK-01 2 DE av2ngFast",
        "WORK-02 CA 39768 Telegram t.me SOSkeyNET",
        "WORK-03 oneclickvpnkeys US 2740",
        "WORK-04 oneclickvpnkeys US 5770",
        "WORK-05 oneclickvpnkeys US 6157",
        "WORK-06 oneclickvpnkeys US 4616",
        "WORK-07 CA 39709 Telegram t.me SOSkeyNET",
        "WORK-08 CA 39775 Telegram t.me SOSkeyNET",
        "WORK-09 35 oneclickvpnkeys",
        "WORK-10 CF20",
        "WORK-11 LINK 10.lowh.net",
        "WORK-12 LINK 15.lowh.net",
        "WORK-13 LINK bel432 xl",
        "WORK-14 LINK sg-trojan.1server.co",
        "WORK-15 LINK VLESS-WS-TLS-443-apt50atpprem",
        "config_free2 2402",
        "config_free2 4595",
        "oneclickvpnkeys DE",
        "oneclickvpnkeys DE 7600",
        "oneclickvpnkeys NL",
        "oneclickvpnkeys PL",
        "oneclickvpnkeys US 2740",
        "oneclickvpnkeys US 4616",
        "oneclickvpnkeys US 5770",
        "oneclickvpnkeys US 6157",
        "v2ray1_ng FR",
        "vpnbaz 7228"
      ],
      "removed_proxies": [
        "27 oneclickvpnkeys",
        "42 oneclickvpnkeys",
        "90 oneclickvpnkeys",
        "Fast Deploy Your Own Worker For Creation Of Configs https telegraph.rayan.dpdns",
        "GAME-01 27 oneclickvpnkeys",
        "GAME-02 v2configlab_ DE",
        "GAME-03 oneclickvpnkeys US 7975",
        "GAME-04 42 oneclickvpnkeys",
        "GAME-05 35 oneclickvpnkeys",
        "GAME-06 CF20",
        "GAME-07 HiByeVPNN",
        "GAME-08 telegram tajrobe_wiki",
        "GAME-09 configV2rayNG FR",
        "GAME-10 V2rayNG3 FR",
        "GEN-01 27 oneclickvpnkeys",
        "GEN-02 v2configlab_ DE",
        "GEN-03 oneclickvpnkeys US 7975",
        "GEN-04 42 oneclickvpnkeys",
        "GEN-05 35 oneclickvpnkeys",
        "GEN-06 Fast Deploy Your Own Worker For Creation Of Configs https telegraph.rayan.dpdns",
        "GEN-07 oneclickvpnkeys US 6784",
        "GEN-08 90 oneclickvpnkeys",
        "GEN-09 CF20",
        "GEN-10 HiByeVPNN",
        "GEN-11 telegram tajrobe_wiki",
        "GEN-12 configV2rayNG FR",
        "GEN-13 V2rayNG3 FR",
        "GEN-14 ProxyEliteVPN",
        "GEN-15 RELAY-104.18.42.54-1541",
        "HiByeVPNN",
        "ID-01 27 oneclickvpnkeys",
        "ID-02 v2configlab_ DE",
        "ID-03 oneclickvpnkeys US 7975",
        "ID-04 42 oneclickvpnkeys",
        "ID-05 35 oneclickvpnkeys",
        "ID-06 LINK 10.lowh.net",
        "ID-07 LINK 15.lowh.net",
        "ID-08 LINK bel432 xl",
        "ID-09 LINK sg-trojan.1server.co",
        "ID-10 LINK VLESS-WS-TLS-443-apt50atpprem",
        "ID-11 LINK VMess-WS-TLS-443-akuku8",
        "ProxyEliteVPN",
        "RELAY-104.18.42.54-1541",
        "SOCIAL-01 27 oneclickvpnkeys",
        "SOCIAL-02 v2configlab_ DE",
        "SOCIAL-03 oneclickvpnkeys US 7975",
        "SOCIAL-04 42 oneclickvpnkeys",
        "SOCIAL-05 35 oneclickvpnkeys",
        "SOCIAL-06 Fast Deploy Your Own Worker For Creation Of Configs https telegraph.rayan.dpdns",
        "SOCIAL-07 CF20",
        "SOCIAL-08 HiByeVPNN",
        "SOCIAL-09 telegram tajrobe_wiki",
        "SOCIAL-10 configV2rayNG FR",
        "SOCIAL-11 V2rayNG3 FR",
        "SOCIAL-12 LINK 10.lowh.net",
        "SOCIAL-13 LINK 15.lowh.net",
        "SOCIAL-14 LINK bel432 xl",
        "SOCIAL-15 LINK sg-trojan.1server.co",
        "STREAM-01 27 oneclickvpnkeys",
        "STREAM-02 v2configlab_ DE",
        "STREAM-03 oneclickvpnkeys US 7975",
        "STREAM-04 42 oneclickvpnkeys",
        "STREAM-05 35 oneclickvpnkeys",
        "STREAM-06 CF20",
        "STREAM-07 HiByeVPNN",
        "STREAM-08 telegram tajrobe_wiki",
        "STREAM-09 configV2rayNG FR",
        "STREAM-10 V2rayNG3 FR",
        "V2rayNG3 FR",
        "WORK-01 27 oneclickvpnkeys",
        "WORK-02 v2configlab_ DE",
        "WORK-03 oneclickvpnkeys US 7975",
        "WORK-04 42 oneclickvpnkeys",
        "WORK-05 35 oneclickvpnkeys",
        "WORK-06 Fast Deploy Your Own Worker For Creation Of Configs https telegraph.rayan.dpdns",
        "WORK-07 CF20",
        "WORK-08 HiByeVPNN",
        "WORK-09 telegram tajrobe_wiki",
        "WORK-10 configV2rayNG FR",
        "WORK-11 V2rayNG3 FR",
        "WORK-12 LINK 10.lowh.net",
        "WORK-13 LINK 15.lowh.net",
        "WORK-14 LINK bel432 xl",
        "WORK-15 LINK sg-trojan.1server.co",
        "oneclickvpnkeys US 6784",
        "oneclickvpnkeys US 7975",
        "telegram tajrobe_wiki",
        "v2configlab_ DE"
      ],
      "added_groups": [
        "URL-TEST TOP 10 INDONESIA"
      ],
      "removed_groups": [
        "URL-TEST TOP 5 INDONESIA"
      ]
    },
    {
      "path": "output/openclash-ready.yaml",
      "exists": true,
      "previous_exists": true,
      "changed": true,
      "size": 65765,
      "sha256": "176d1344ad0fa8bb3b1bd34343f38a4fbad17b80584c365d04e1776d20722037",
      "previous_size": 60506,
      "previous_sha256": "e2feb250c69b175d6a6db5e1c0287e821be2fded6455e7368be0586443537c38",
      "proxy_count": 140,
      "previous_proxy_count": 130,
      "groups_count": 23,
      "previous_groups_count": 23,
      "rules_count": 67,
      "added_proxies": [
        "CA 39693 Telegram t.me SOSkeyNET",
        "CA 39709 Telegram t.me SOSkeyNET",
        "CA 39768 Telegram t.me SOSkeyNET",
        "CA 39775 Telegram t.me SOSkeyNET",
        "DE t.me Natrixo AA",
        "Fast Deploy Your Own Worker For Creation Of Configs https telegraph.rayan-config 9998",
        "FreakConfig FR",
        "FreeConffning",
        "GAME-01 2 DE av2ngFast",
        "GAME-02 CA 39768 Telegram t.me SOSkeyNET",
        "GAME-03 oneclickvpnkeys US 2740",
        "GAME-04 oneclickvpnkeys US 5770",
        "GAME-05 oneclickvpnkeys US 6157",
        "GAME-06 oneclickvpnkeys US 4616",
        "GAME-07 CA 39709 Telegram t.me SOSkeyNET",
        "GAME-08 CA 39775 Telegram t.me SOSkeyNET",
        "GAME-09 35 oneclickvpnkeys",
        "GAME-10 CF20",
        "GEN-01 2 DE av2ngFast",
        "GEN-02 CA 39768 Telegram t.me SOSkeyNET",
        "GEN-03 oneclickvpnkeys US 2740",
        "GEN-04 oneclickvpnkeys US 5770",
        "GEN-05 oneclickvpnkeys US 6157",
        "GEN-06 oneclickvpnkeys US 4616",
        "GEN-07 CA 39709 Telegram t.me SOSkeyNET",
        "GEN-08 CA 39775 Telegram t.me SOSkeyNET",
        "GEN-09 35 oneclickvpnkeys",
        "GEN-10 CF20",
        "GEN-11 oneclickvpnkeys US",
        "GEN-12 V2rayNG3 US",
        "GEN-13 oneclickvpnkeys US 4666",
        "GEN-14 oneclickvpnkeys US 5868",
        "GEN-15 oneclickvpnkeys US 6470",
        "ID-01 2 DE av2ngFast",
        "ID-02 CA 39768 Telegram t.me SOSkeyNET",
        "ID-03 oneclickvpnkeys US 2740",
        "ID-04 oneclickvpnkeys US 5770",
        "ID-05 oneclickvpnkeys US 6157",
        "ID-06 oneclickvpnkeys US 4616",
        "ID-07 CA 39709 Telegram t.me SOSkeyNET",
        "ID-08 CA 39775 Telegram t.me SOSkeyNET",
        "ID-09 35 oneclickvpnkeys",
        "ID-10 CF20",
        "ID-11 DE t.me Natrixo AA",
        "ID-12 LINK 10.lowh.net",
        "ID-13 LINK 15.lowh.net",
        "ID-14 LINK bel432 xl",
        "ID-15 LINK sg-trojan.1server.co",
        "ID-16 LINK VLESS-WS-TLS-443-apt50atpprem",
        "ID-17 LINK VMess-WS-TLS-443-akuku8",
        "KAFING_2 4061",
        "SOCIAL-01 2 DE av2ngFast",
        "SOCIAL-02 CA 39768 Telegram t.me SOSkeyNET",
        "SOCIAL-03 oneclickvpnkeys US 2740",
        "SOCIAL-04 oneclickvpnkeys US 5770",
        "SOCIAL-05 oneclickvpnkeys US 6157",
        "SOCIAL-06 oneclickvpnkeys US 4616",
        "SOCIAL-07 CA 39709 Telegram t.me SOSkeyNET",
        "SOCIAL-08 CA 39775 Telegram t.me SOSkeyNET",
        "SOCIAL-09 35 oneclickvpnkeys",
        "SOCIAL-10 CF20",
        "SOCIAL-11 https telegraph.rayan-config.workers.dev persian 6140",
        "SOCIAL-12 Fast Deploy Your Own Worker For Creation Of Configs https telegraph.rayan-config 9998",
        "SOCIAL-13 Fast Deploy Your Own Worker For Creation Of Configs https telegraph.rayan.dpdns",
        "SOCIAL-14 v2configlab",
        "SOCIAL-15 CA 39693 Telegram t.me SOSkeyNET",
        "STREAM-01 2 DE av2ngFast",
        "STREAM-02 CA 39768 Telegram t.me SOSkeyNET",
        "STREAM-03 oneclickvpnkeys US 2740",
        "STREAM-04 oneclickvpnkeys US 5770",
        "STREAM-05 oneclickvpnkeys US 6157",
        "STREAM-06 oneclickvpnkeys US 4616",
        "STREAM-07 CA 39709 Telegram t.me SOSkeyNET",
        "STREAM-08 CA 39775 Telegram t.me SOSkeyNET",
        "STREAM-09 35 oneclickvpnkeys",
        "STREAM-10 CF20",
        "US Join Telegram Farah_VPN US",
        "V2rayNG3 US",
        "WORK-01 2 DE av2ngFast",
        "WORK-02 CA 39768 Telegram t.me SOSkeyNET",
        "WORK-03 oneclickvpnkeys US 2740",
        "WORK-04 oneclickvpnkeys US 5770",
        "WORK-05 oneclickvpnkeys US 6157",
        "WORK-06 oneclickvpnkeys US 4616",
        "WORK-07 CA 39709 Telegram t.me SOSkeyNET",
        "WORK-08 CA 39775 Telegram t.me SOSkeyNET",
        "WORK-09 35 oneclickvpnkeys",
        "WORK-11 https telegraph.rayan-config.workers.dev persian 6140",
        "WORK-12 Fast Deploy Your Own Worker For Creation Of Configs https telegraph.rayan-config 9998",
        "WORK-13 Fast Deploy Your Own Worker For Creation Of Configs https telegraph.rayan.dpdns",
        "WORK-14 LINK 10.lowh.net",
        "WORK-15 LINK 15.lowh.net",
        "config_free2 2402",
        "config_free2 4595",
        "https telegraph.rayan-config.workers.dev persian 6140",
        "oneclickvpnkeys DE 7600",
        "oneclickvpnkeys US 2740",
        "oneclickvpnkeys US 3072",
        "oneclickvpnkeys US 3799",
        "oneclickvpnkeys US 4616"
      ],
      "removed_proxies": [
        "26 oneclickvpnkeys",
        "27 oneclickvpnkeys",
        "36 oneclickvpnkeys",
        "42 oneclickvpnkeys",
        "76 oneclickvpnkeys",
        "79 oneclickvpnkeys",
        "90 oneclickvpnkeys",
        "By EbraSha 2179",
        "Fast Deploy Your Own Worker For Creation Of Configs https telegraph.rayan-config 6105",
        "GAME-01 27 oneclickvpnkeys",
        "GAME-02 v2configlab_ DE",
        "GAME-03 oneclickvpnkeys US 7975",
        "GAME-04 42 oneclickvpnkeys",
        "GAME-05 35 oneclickvpnkeys",
        "GAME-06 CF20",
        "GAME-07 HiByeVPNN",
        "GAME-08 telegram tajrobe_wiki",
        "GAME-09 configV2rayNG FR",
        "GAME-10 V2rayNG3 FR",
        "GEN-01 27 oneclickvpnkeys",
        "GEN-02 v2configlab_ DE",
        "GEN-03 oneclickvpnkeys US 7975",
        "GEN-04 42 oneclickvpnkeys",
        "GEN-05 35 oneclickvpnkeys",
        "GEN-06 Fast Deploy Your Own Worker For Creation Of Configs https telegraph.rayan.dpdns",
        "GEN-07 https telegraph.rayan.dpdns.org persian",
        "GEN-08 https telegraph.rayan-config.workers.dev persian",
        "GEN-09 https telegraph.rayan-config.workers.dev persian 9713",
        "GEN-10 Fast Deploy Your Own Worker For Creation Of Configs https telegraph.rayan-config 6105",
        "GEN-11 oneclickvpnkeys US 6784",
        "GEN-12 oneclickvpnkeys US 7902",
        "GEN-13 79 oneclickvpnkeys",
        "GEN-14 v2configlab",
        "GEN-15 2 DE av2ngFast",
        "ID-01 27 oneclickvpnkeys",
        "ID-02 v2configlab_ DE",
        "ID-03 oneclickvpnkeys US 7975",
        "ID-04 42 oneclickvpnkeys",
        "ID-05 35 oneclickvpnkeys",
        "ID-06 LINK 10.lowh.net",
        "ID-07 LINK 15.lowh.net",
        "ID-08 LINK bel432 xl",
        "ID-09 LINK sg-trojan.1server.co",
        "ID-10 LINK VLESS-WS-TLS-443-apt50atpprem",
        "ID-11 LINK VMess-WS-TLS-443-akuku8",
        "KAFING_2 4784",
        "ProxyEliteVPN",
        "RELAY-104.18.42.54-1541",
        "SOCIAL-01 27 oneclickvpnkeys",
        "SOCIAL-02 v2configlab_ DE",
        "SOCIAL-03 oneclickvpnkeys US 7975",
        "SOCIAL-04 42 oneclickvpnkeys",
        "SOCIAL-05 35 oneclickvpnkeys",
        "SOCIAL-06 Fast Deploy Your Own Worker For Creation Of Configs https telegraph.rayan.dpdns",
        "SOCIAL-07 https telegraph.rayan-config.workers.dev persian",
        "SOCIAL-08 https telegraph.rayan-config.workers.dev persian 9713",
        "SOCIAL-09 Fast Deploy Your Own Worker For Creation Of Configs https telegraph.rayan-config 6105",
        "SOCIAL-10 v2configlab",
        "SOCIAL-11 CF20",
        "SOCIAL-12 HiByeVPNN",
        "SOCIAL-13 telegram tajrobe_wiki",
        "SOCIAL-14 configV2rayNG FR",
        "SOCIAL-15 V2rayNG3 FR",
        "STREAM-01 27 oneclickvpnkeys",
        "STREAM-02 v2configlab_ DE",
        "STREAM-03 oneclickvpnkeys US 7975",
        "STREAM-04 42 oneclickvpnkeys",
        "STREAM-05 35 oneclickvpnkeys",
        "STREAM-06 CF20",
        "STREAM-07 HiByeVPNN",
        "STREAM-08 telegram tajrobe_wiki",
        "STREAM-09 configV2rayNG FR",
        "STREAM-10 V2rayNG3 FR",
        "V2rayNG3 FR",
        "VLESS",
        "WORK-01 27 oneclickvpnkeys",
        "WORK-02 v2configlab_ DE",
        "WORK-03 oneclickvpnkeys US 7975",
        "WORK-04 42 oneclickvpnkeys",
        "WORK-05 35 oneclickvpnkeys",
        "WORK-06 Fast Deploy Your Own Worker For Creation Of Configs https telegraph.rayan.dpdns",
        "WORK-07 https telegraph.rayan-config.workers.dev persian",
        "WORK-08 https telegraph.rayan-config.workers.dev persian 9713",
        "WORK-09 Fast Deploy Your Own Worker For Creation Of Configs https telegraph.rayan-config 6105",
        "WORK-11 HiByeVPNN",
        "WORK-12 telegram tajrobe_wiki",
        "WORK-13 configV2rayNG FR",
        "WORK-14 V2rayNG3 FR",
        "WORK-15 LINK 10.lowh.net",
        "chillguy_vpn",
        "config_free2 7235",
        "https telegraph.rayan-config.workers.dev persian",
        "https telegraph.rayan-config.workers.dev persian 9713",
        "oneclickvpnkeys DE 5963",
        "oneclickvpnkeys US 6784",
        "oneclickvpnkeys US 7902",
        "oneclickvpnkeys US 7975",
        "telegram tajrobe_wiki",
        "vpnbaz 9219"
      ],
      "added_groups": [
        "URL-TEST TOP 10 INDONESIA"
      ],
      "removed_groups": [
        "URL-TEST TOP 5 INDONESIA"
      ]
    },
    {
      "path": "output/social_media.yaml",
      "exists": true,
      "previous_exists": true,
      "changed": true,
      "size": 40299,
      "sha256": "0eb30d8cc73f932452180407800c5161ac45bd20baf8f28936dd4334393f05ba",
      "previous_size": 36786,
      "previous_sha256": "a02a9e71dcb7822d57e26878fdb62ebc22252c666f86dde993548d59d08aa2b8",
      "proxy_count": 92,
      "previous_proxy_count": 87,
      "groups_count": 11,
      "previous_groups_count": 11,
      "rules_count": 67,
      "added_proxies": [
        "2 DE av2ngFast",
        "CA 39709 Telegram t.me SOSkeyNET",
        "CA 39768 Telegram t.me SOSkeyNET",
        "CA 39775 Telegram t.me SOSkeyNET",
        "GAME-01 2 DE av2ngFast",
        "GAME-02 CA 39768 Telegram t.me SOSkeyNET",
        "GAME-03 oneclickvpnkeys US 2740",
        "GAME-04 oneclickvpnkeys US 5770",
        "GAME-05 oneclickvpnkeys US 6157",
        "GAME-06 oneclickvpnkeys US 4616",
        "GAME-07 CA 39709 Telegram t.me SOSkeyNET",
        "GAME-08 CA 39775 Telegram t.me SOSkeyNET",
        "GAME-09 35 oneclickvpnkeys",
        "GAME-10 CF20",
        "GEN-01 2 DE av2ngFast",
        "GEN-02 CA 39768 Telegram t.me SOSkeyNET",
        "GEN-03 oneclickvpnkeys US 2740",
        "GEN-04 oneclickvpnkeys US 5770",
        "GEN-05 oneclickvpnkeys US 6157",
        "GEN-06 oneclickvpnkeys US 4616",
        "GEN-07 CA 39709 Telegram t.me SOSkeyNET",
        "GEN-08 CA 39775 Telegram t.me SOSkeyNET",
        "GEN-09 35 oneclickvpnkeys",
        "GEN-10 CF20",
        "ID-01 2 DE av2ngFast",
        "ID-02 CA 39768 Telegram t.me SOSkeyNET",
        "ID-03 oneclickvpnkeys US 2740",
        "ID-04 oneclickvpnkeys US 5770",
        "ID-05 oneclickvpnkeys US 6157",
        "ID-06 oneclickvpnkeys US 4616",
        "ID-07 CA 39709 Telegram t.me SOSkeyNET",
        "ID-08 CA 39775 Telegram t.me SOSkeyNET",
        "ID-09 35 oneclickvpnkeys",
        "ID-10 CF20",
        "ID-11 LINK bel432 xl",
        "SOCIAL-01 2 DE av2ngFast",
        "SOCIAL-02 CA 39768 Telegram t.me SOSkeyNET",
        "SOCIAL-03 oneclickvpnkeys US 2740",
        "SOCIAL-04 oneclickvpnkeys US 5770",
        "SOCIAL-05 oneclickvpnkeys US 6157",
        "SOCIAL-06 oneclickvpnkeys US 4616",
        "SOCIAL-07 CA 39709 Telegram t.me SOSkeyNET",
        "SOCIAL-08 CA 39775 Telegram t.me SOSkeyNET",
        "SOCIAL-09 35 oneclickvpnkeys",
        "SOCIAL-10 CF20",
        "STREAM-01 2 DE av2ngFast",
        "STREAM-02 CA 39768 Telegram t.me SOSkeyNET",
        "STREAM-03 oneclickvpnkeys US 2740",
        "STREAM-04 oneclickvpnkeys US 5770",
        "STREAM-05 oneclickvpnkeys US 6157",
        "STREAM-06 oneclickvpnkeys US 4616",
        "STREAM-07 CA 39709 Telegram t.me SOSkeyNET",
        "STREAM-08 CA 39775 Telegram t.me SOSkeyNET",
        "STREAM-09 35 oneclickvpnkeys",
        "STREAM-10 CF20",
        "WORK-01 2 DE av2ngFast",
        "WORK-02 CA 39768 Telegram t.me SOSkeyNET",
        "WORK-03 oneclickvpnkeys US 2740",
        "WORK-04 oneclickvpnkeys US 5770",
        "WORK-05 oneclickvpnkeys US 6157",
        "WORK-06 oneclickvpnkeys US 4616",
        "WORK-07 CA 39709 Telegram t.me SOSkeyNET",
        "WORK-08 CA 39775 Telegram t.me SOSkeyNET",
        "WORK-09 35 oneclickvpnkeys",
        "WORK-10 CF20",
        "oneclickvpnkeys US 2740",
        "oneclickvpnkeys US 4616",
        "oneclickvpnkeys US 5770",
        "oneclickvpnkeys US 6157"
      ],
      "removed_proxies": [
        "27 oneclickvpnkeys",
        "42 oneclickvpnkeys",
        "GAME-01 27 oneclickvpnkeys",
        "GAME-02 v2configlab_ DE",
        "GAME-03 oneclickvpnkeys US 7975",
        "GAME-04 42 oneclickvpnkeys",
        "GAME-05 35 oneclickvpnkeys",
        "GAME-06 CF20",
        "GAME-07 HiByeVPNN",
        "GAME-08 telegram tajrobe_wiki",
        "GAME-09 configV2rayNG FR",
        "GAME-10 V2rayNG3 FR",
        "GEN-01 27 oneclickvpnkeys",
        "GEN-02 v2configlab_ DE",
        "GEN-03 oneclickvpnkeys US 7975",
        "GEN-04 42 oneclickvpnkeys",
        "GEN-05 35 oneclickvpnkeys",
        "GEN-06 CF20",
        "GEN-07 HiByeVPNN",
        "GEN-08 telegram tajrobe_wiki",
        "GEN-09 configV2rayNG FR",
        "GEN-10 V2rayNG3 FR",
        "HiByeVPNN",
        "ID-01 27 oneclickvpnkeys",
        "ID-02 v2configlab_ DE",
        "ID-03 oneclickvpnkeys US 7975",
        "ID-04 42 oneclickvpnkeys",
        "ID-05 35 oneclickvpnkeys",
        "ID-06 LINK bel432 xl",
        "SOCIAL-01 27 oneclickvpnkeys",
        "SOCIAL-02 v2configlab_ DE",
        "SOCIAL-03 oneclickvpnkeys US 7975",
        "SOCIAL-04 42 oneclickvpnkeys",
        "SOCIAL-05 35 oneclickvpnkeys",
        "SOCIAL-06 CF20",
        "SOCIAL-07 HiByeVPNN",
        "SOCIAL-08 telegram tajrobe_wiki",
        "SOCIAL-09 configV2rayNG FR",
        "SOCIAL-10 V2rayNG3 FR",
        "STREAM-01 27 oneclickvpnkeys",
        "STREAM-02 v2configlab_ DE",
        "STREAM-03 oneclickvpnkeys US 7975",
        "STREAM-04 42 oneclickvpnkeys",
        "STREAM-05 35 oneclickvpnkeys",
        "STREAM-06 CF20",
        "STREAM-07 HiByeVPNN",
        "STREAM-08 telegram tajrobe_wiki",
        "STREAM-09 configV2rayNG FR",
        "STREAM-10 V2rayNG3 FR",
        "V2rayNG3 FR",
        "WORK-01 27 oneclickvpnkeys",
        "WORK-02 v2configlab_ DE",
        "WORK-03 oneclickvpnkeys US 7975",
        "WORK-04 42 oneclickvpnkeys",
        "WORK-05 35 oneclickvpnkeys",
        "WORK-06 CF20",
        "WORK-07 HiByeVPNN",
        "WORK-08 telegram tajrobe_wiki",
        "WORK-09 configV2rayNG FR",
        "WORK-10 V2rayNG3 FR",
        "configV2rayNG FR",
        "oneclickvpnkeys US 7975",
        "telegram tajrobe_wiki",
        "v2configlab_ DE"
      ],
      "added_groups": [],
      "removed_groups": []
    },
    {
      "path": "output/streaming.yaml",
      "exists": true,
      "previous_exists": true,
      "changed": true,
      "size": 38499,
      "sha256": "6212cf559e3cce7727ed0cd7cae78b91bcc36369e1f71ece71c1dc1ecd25440c",
      "previous_size": 34986,
      "previous_sha256": "4449d7473caa2a377551ccd347ff185732a3843d82b39e16796ebc82da09712e",
      "proxy_count": 87,
      "previous_proxy_count": 82,
      "groups_count": 11,
      "previous_groups_count": 11,
      "rules_count": 67,
      "added_proxies": [
        "2 DE av2ngFast",
        "CA 39709 Telegram t.me SOSkeyNET",
        "CA 39768 Telegram t.me SOSkeyNET",
        "CA 39775 Telegram t.me SOSkeyNET",
        "GAME-01 2 DE av2ngFast",
        "GAME-02 CA 39768 Telegram t.me SOSkeyNET",
        "GAME-03 oneclickvpnkeys US 2740",
        "GAME-04 oneclickvpnkeys US 5770",
        "GAME-05 oneclickvpnkeys US 6157",
        "GAME-06 oneclickvpnkeys US 4616",
        "GAME-07 CA 39709 Telegram t.me SOSkeyNET",
        "GAME-08 CA 39775 Telegram t.me SOSkeyNET",
        "GAME-09 35 oneclickvpnkeys",
        "GAME-10 CF20",
        "GEN-01 2 DE av2ngFast",
        "GEN-02 CA 39768 Telegram t.me SOSkeyNET",
        "GEN-03 oneclickvpnkeys US 2740",
        "GEN-04 oneclickvpnkeys US 5770",
        "GEN-05 oneclickvpnkeys US 6157",
        "GEN-06 oneclickvpnkeys US 4616",
        "GEN-07 CA 39709 Telegram t.me SOSkeyNET",
        "GEN-08 CA 39775 Telegram t.me SOSkeyNET",
        "GEN-09 35 oneclickvpnkeys",
        "GEN-10 CF20",
        "ID-01 2 DE av2ngFast",
        "ID-02 CA 39768 Telegram t.me SOSkeyNET",
        "ID-03 oneclickvpnkeys US 2740",
        "ID-04 oneclickvpnkeys US 5770",
        "ID-05 oneclickvpnkeys US 6157",
        "ID-06 oneclickvpnkeys US 4616",
        "ID-07 CA 39709 Telegram t.me SOSkeyNET",
        "ID-08 CA 39775 Telegram t.me SOSkeyNET",
        "ID-09 35 oneclickvpnkeys",
        "ID-10 CF20",
        "ID-11 LINK bel432 xl",
        "SOCIAL-01 2 DE av2ngFast",
        "SOCIAL-02 CA 39768 Telegram t.me SOSkeyNET",
        "SOCIAL-03 oneclickvpnkeys US 2740",
        "SOCIAL-04 oneclickvpnkeys US 5770",
        "SOCIAL-05 oneclickvpnkeys US 6157",
        "SOCIAL-06 oneclickvpnkeys US 4616",
        "SOCIAL-07 CA 39709 Telegram t.me SOSkeyNET",
        "SOCIAL-08 CA 39775 Telegram t.me SOSkeyNET",
        "SOCIAL-09 35 oneclickvpnkeys",
        "SOCIAL-10 CF20",
        "STREAM-01 2 DE av2ngFast",
        "STREAM-02 CA 39768 Telegram t.me SOSkeyNET",
        "STREAM-03 oneclickvpnkeys US 2740",
        "STREAM-04 oneclickvpnkeys US 5770",
        "STREAM-05 oneclickvpnkeys US 6157",
        "STREAM-06 oneclickvpnkeys US 4616",
        "STREAM-07 CA 39709 Telegram t.me SOSkeyNET",
        "STREAM-08 CA 39775 Telegram t.me SOSkeyNET",
        "STREAM-09 35 oneclickvpnkeys",
        "STREAM-10 CF20",
        "WORK-01 2 DE av2ngFast",
        "WORK-02 CA 39768 Telegram t.me SOSkeyNET",
        "WORK-03 oneclickvpnkeys US 2740",
        "WORK-04 oneclickvpnkeys US 5770",
        "WORK-05 oneclickvpnkeys US 6157",
        "WORK-06 oneclickvpnkeys US 4616",
        "WORK-07 CA 39709 Telegram t.me SOSkeyNET",
        "WORK-08 CA 39775 Telegram t.me SOSkeyNET",
        "WORK-09 35 oneclickvpnkeys",
        "WORK-10 CF20",
        "oneclickvpnkeys US 2740",
        "oneclickvpnkeys US 4616",
        "oneclickvpnkeys US 5770",
        "oneclickvpnkeys US 6157"
      ],
      "removed_proxies": [
        "27 oneclickvpnkeys",
        "42 oneclickvpnkeys",
        "GAME-01 27 oneclickvpnkeys",
        "GAME-02 v2configlab_ DE",
        "GAME-03 oneclickvpnkeys US 7975",
        "GAME-04 42 oneclickvpnkeys",
        "GAME-05 35 oneclickvpnkeys",
        "GAME-06 CF20",
        "GAME-07 HiByeVPNN",
        "GAME-08 telegram tajrobe_wiki",
        "GAME-09 configV2rayNG FR",
        "GAME-10 V2rayNG3 FR",
        "GEN-01 27 oneclickvpnkeys",
        "GEN-02 v2configlab_ DE",
        "GEN-03 oneclickvpnkeys US 7975",
        "GEN-04 42 oneclickvpnkeys",
        "GEN-05 35 oneclickvpnkeys",
        "GEN-06 CF20",
        "GEN-07 HiByeVPNN",
        "GEN-08 telegram tajrobe_wiki",
        "GEN-09 configV2rayNG FR",
        "GEN-10 V2rayNG3 FR",
        "HiByeVPNN",
        "ID-01 27 oneclickvpnkeys",
        "ID-02 v2configlab_ DE",
        "ID-03 oneclickvpnkeys US 7975",
        "ID-04 42 oneclickvpnkeys",
        "ID-05 35 oneclickvpnkeys",
        "ID-06 LINK bel432 xl",
        "SOCIAL-01 27 oneclickvpnkeys",
        "SOCIAL-02 v2configlab_ DE",
        "SOCIAL-03 oneclickvpnkeys US 7975",
        "SOCIAL-04 42 oneclickvpnkeys",
        "SOCIAL-05 35 oneclickvpnkeys",
        "SOCIAL-06 CF20",
        "SOCIAL-07 HiByeVPNN",
        "SOCIAL-08 telegram tajrobe_wiki",
        "SOCIAL-09 configV2rayNG FR",
        "SOCIAL-10 V2rayNG3 FR",
        "STREAM-01 27 oneclickvpnkeys",
        "STREAM-02 v2configlab_ DE",
        "STREAM-03 oneclickvpnkeys US 7975",
        "STREAM-04 42 oneclickvpnkeys",
        "STREAM-05 35 oneclickvpnkeys",
        "STREAM-06 CF20",
        "STREAM-07 HiByeVPNN",
        "STREAM-08 telegram tajrobe_wiki",
        "STREAM-09 configV2rayNG FR",
        "STREAM-10 V2rayNG3 FR",
        "V2rayNG3 FR",
        "WORK-01 27 oneclickvpnkeys",
        "WORK-02 v2configlab_ DE",
        "WORK-03 oneclickvpnkeys US 7975",
        "WORK-04 42 oneclickvpnkeys",
        "WORK-05 35 oneclickvpnkeys",
        "WORK-06 CF20",
        "WORK-07 HiByeVPNN",
        "WORK-08 telegram tajrobe_wiki",
        "WORK-09 configV2rayNG FR",
        "WORK-10 V2rayNG3 FR",
        "configV2rayNG FR",
        "oneclickvpnkeys US 7975",
        "telegram tajrobe_wiki",
        "v2configlab_ DE"
      ],
      "added_groups": [],
      "removed_groups": []
    },
    {
      "path": "output/strict_alive.yaml",
      "exists": true,
      "previous_exists": true,
      "changed": true,
      "size": 65319,
      "sha256": "747d45d3e7aa7daaef7b1f39fcf2380b285fd063cb75c4a7efcebb0bd221031e",
      "previous_size": 60012,
      "previous_sha256": "ee6d51f4fbd6f54cb894a331fb19c4b9c14cc6ee965c4d0ab62be238e18f372f",
      "proxy_count": 140,
      "previous_proxy_count": 130,
      "groups_count": 22,
      "previous_groups_count": 22,
      "rules_count": 67,
      "added_proxies": [
        "CA 39693 Telegram t.me SOSkeyNET",
        "CA 39709 Telegram t.me SOSkeyNET",
        "CA 39768 Telegram t.me SOSkeyNET",
        "CA 39775 Telegram t.me SOSkeyNET",
        "DE t.me Natrixo AA",
        "Fast Deploy Your Own Worker For Creation Of Configs https telegraph.rayan-config 9998",
        "FreakConfig FR",
        "FreeConffning",
        "GAME-01 2 DE av2ngFast",
        "GAME-02 CA 39768 Telegram t.me SOSkeyNET",
        "GAME-03 oneclickvpnkeys US 2740",
        "GAME-04 oneclickvpnkeys US 5770",
        "GAME-05 oneclickvpnkeys US 6157",
        "GAME-06 oneclickvpnkeys US 4616",
        "GAME-07 CA 39709 Telegram t.me SOSkeyNET",
        "GAME-08 CA 39775 Telegram t.me SOSkeyNET",
        "GAME-09 35 oneclickvpnkeys",
        "GAME-10 CF20",
        "GEN-01 2 DE av2ngFast",
        "GEN-02 CA 39768 Telegram t.me SOSkeyNET",
        "GEN-03 oneclickvpnkeys US 2740",
        "GEN-04 oneclickvpnkeys US 5770",
        "GEN-05 oneclickvpnkeys US 6157",
        "GEN-06 oneclickvpnkeys US 4616",
        "GEN-07 CA 39709 Telegram t.me SOSkeyNET",
        "GEN-08 CA 39775 Telegram t.me SOSkeyNET",
        "GEN-09 35 oneclickvpnkeys",
        "GEN-10 CF20",
        "GEN-11 oneclickvpnkeys US",
        "GEN-12 V2rayNG3 US",
        "GEN-13 oneclickvpnkeys US 4666",
        "GEN-14 oneclickvpnkeys US 5868",
        "GEN-15 oneclickvpnkeys US 6470",
        "ID-01 2 DE av2ngFast",
        "ID-02 CA 39768 Telegram t.me SOSkeyNET",
        "ID-03 oneclickvpnkeys US 2740",
        "ID-04 oneclickvpnkeys US 5770",
        "ID-05 oneclickvpnkeys US 6157",
        "ID-06 oneclickvpnkeys US 4616",
        "ID-07 CA 39709 Telegram t.me SOSkeyNET",
        "ID-08 CA 39775 Telegram t.me SOSkeyNET",
        "ID-09 35 oneclickvpnkeys",
        "ID-10 CF20",
        "ID-11 DE t.me Natrixo AA",
        "ID-12 LINK 10.lowh.net",
        "ID-13 LINK 15.lowh.net",
        "ID-14 LINK bel432 xl",
        "ID-15 LINK sg-trojan.1server.co",
        "ID-16 LINK VLESS-WS-TLS-443-apt50atpprem",
        "ID-17 LINK VMess-WS-TLS-443-akuku8",
        "KAFING_2 4061",
        "SOCIAL-01 2 DE av2ngFast",
        "SOCIAL-02 CA 39768 Telegram t.me SOSkeyNET",
        "SOCIAL-03 oneclickvpnkeys US 2740",
        "SOCIAL-04 oneclickvpnkeys US 5770",
        "SOCIAL-05 oneclickvpnkeys US 6157",
        "SOCIAL-06 oneclickvpnkeys US 4616",
        "SOCIAL-07 CA 39709 Telegram t.me SOSkeyNET",
        "SOCIAL-08 CA 39775 Telegram t.me SOSkeyNET",
        "SOCIAL-09 35 oneclickvpnkeys",
        "SOCIAL-10 CF20",
        "SOCIAL-11 https telegraph.rayan-config.workers.dev persian 6140",
        "SOCIAL-12 Fast Deploy Your Own Worker For Creation Of Configs https telegraph.rayan-config 9998",
        "SOCIAL-13 Fast Deploy Your Own Worker For Creation Of Configs https telegraph.rayan.dpdns",
        "SOCIAL-14 v2configlab",
        "SOCIAL-15 CA 39693 Telegram t.me SOSkeyNET",
        "STREAM-01 2 DE av2ngFast",
        "STREAM-02 CA 39768 Telegram t.me SOSkeyNET",
        "STREAM-03 oneclickvpnkeys US 2740",
        "STREAM-04 oneclickvpnkeys US 5770",
        "STREAM-05 oneclickvpnkeys US 6157",
        "STREAM-06 oneclickvpnkeys US 4616",
        "STREAM-07 CA 39709 Telegram t.me SOSkeyNET",
        "STREAM-08 CA 39775 Telegram t.me SOSkeyNET",
        "STREAM-09 35 oneclickvpnkeys",
        "STREAM-10 CF20",
        "US Join Telegram Farah_VPN US",
        "V2rayNG3 US",
        "WORK-01 2 DE av2ngFast",
        "WORK-02 CA 39768 Telegram t.me SOSkeyNET",
        "WORK-03 oneclickvpnkeys US 2740",
        "WORK-04 oneclickvpnkeys US 5770",
        "WORK-05 oneclickvpnkeys US 6157",
        "WORK-06 oneclickvpnkeys US 4616",
        "WORK-07 CA 39709 Telegram t.me SOSkeyNET",
        "WORK-08 CA 39775 Telegram t.me SOSkeyNET",
        "WORK-09 35 oneclickvpnkeys",
        "WORK-11 https telegraph.rayan-config.workers.dev persian 6140",
        "WORK-12 Fast Deploy Your Own Worker For Creation Of Configs https telegraph.rayan-config 9998",
        "WORK-13 Fast Deploy Your Own Worker For Creation Of Configs https telegraph.rayan.dpdns",
        "WORK-14 LINK 10.lowh.net",
        "WORK-15 LINK 15.lowh.net",
        "config_free2 2402",
        "config_free2 4595",
        "https telegraph.rayan-config.workers.dev persian 6140",
        "oneclickvpnkeys DE 7600",
        "oneclickvpnkeys US 2740",
        "oneclickvpnkeys US 3072",
        "oneclickvpnkeys US 3799",
        "oneclickvpnkeys US 4616"
      ],
      "removed_proxies": [
        "26 oneclickvpnkeys",
        "27 oneclickvpnkeys",
        "36 oneclickvpnkeys",
        "42 oneclickvpnkeys",
        "76 oneclickvpnkeys",
        "79 oneclickvpnkeys",
        "90 oneclickvpnkeys",
        "By EbraSha 2179",
        "Fast Deploy Your Own Worker For Creation Of Configs https telegraph.rayan-config 6105",
        "GAME-01 27 oneclickvpnkeys",
        "GAME-02 v2configlab_ DE",
        "GAME-03 oneclickvpnkeys US 7975",
        "GAME-04 42 oneclickvpnkeys",
        "GAME-05 35 oneclickvpnkeys",
        "GAME-06 CF20",
        "GAME-07 HiByeVPNN",
        "GAME-08 telegram tajrobe_wiki",
        "GAME-09 configV2rayNG FR",
        "GAME-10 V2rayNG3 FR",
        "GEN-01 27 oneclickvpnkeys",
        "GEN-02 v2configlab_ DE",
        "GEN-03 oneclickvpnkeys US 7975",
        "GEN-04 42 oneclickvpnkeys",
        "GEN-05 35 oneclickvpnkeys",
        "GEN-06 Fast Deploy Your Own Worker For Creation Of Configs https telegraph.rayan.dpdns",
        "GEN-07 https telegraph.rayan.dpdns.org persian",
        "GEN-08 https telegraph.rayan-config.workers.dev persian",
        "GEN-09 https telegraph.rayan-config.workers.dev persian 9713",
        "GEN-10 Fast Deploy Your Own Worker For Creation Of Configs https telegraph.rayan-config 6105",
        "GEN-11 oneclickvpnkeys US 6784",
        "GEN-12 oneclickvpnkeys US 7902",
        "GEN-13 79 oneclickvpnkeys",
        "GEN-14 v2configlab",
        "GEN-15 2 DE av2ngFast",
        "ID-01 27 oneclickvpnkeys",
        "ID-02 v2configlab_ DE",
        "ID-03 oneclickvpnkeys US 7975",
        "ID-04 42 oneclickvpnkeys",
        "ID-05 35 oneclickvpnkeys",
        "ID-06 LINK 10.lowh.net",
        "ID-07 LINK 15.lowh.net",
        "ID-08 LINK bel432 xl",
        "ID-09 LINK sg-trojan.1server.co",
        "ID-10 LINK VLESS-WS-TLS-443-apt50atpprem",
        "ID-11 LINK VMess-WS-TLS-443-akuku8",
        "KAFING_2 4784",
        "ProxyEliteVPN",
        "RELAY-104.18.42.54-1541",
        "SOCIAL-01 27 oneclickvpnkeys",
        "SOCIAL-02 v2configlab_ DE",
        "SOCIAL-03 oneclickvpnkeys US 7975",
        "SOCIAL-04 42 oneclickvpnkeys",
        "SOCIAL-05 35 oneclickvpnkeys",
        "SOCIAL-06 Fast Deploy Your Own Worker For Creation Of Configs https telegraph.rayan.dpdns",
        "SOCIAL-07 https telegraph.rayan-config.workers.dev persian",
        "SOCIAL-08 https telegraph.rayan-config.workers.dev persian 9713",
        "SOCIAL-09 Fast Deploy Your Own Worker For Creation Of Configs https telegraph.rayan-config 6105",
        "SOCIAL-10 v2configlab",
        "SOCIAL-11 CF20",
        "SOCIAL-12 HiByeVPNN",
        "SOCIAL-13 telegram tajrobe_wiki",
        "SOCIAL-14 configV2rayNG FR",
        "SOCIAL-15 V2rayNG3 FR",
        "STREAM-01 27 oneclickvpnkeys",
        "STREAM-02 v2configlab_ DE",
        "STREAM-03 oneclickvpnkeys US 7975",
        "STREAM-04 42 oneclickvpnkeys",
        "STREAM-05 35 oneclickvpnkeys",
        "STREAM-06 CF20",
        "STREAM-07 HiByeVPNN",
        "STREAM-08 telegram tajrobe_wiki",
        "STREAM-09 configV2rayNG FR",
        "STREAM-10 V2rayNG3 FR",
        "V2rayNG3 FR",
        "VLESS",
        "WORK-01 27 oneclickvpnkeys",
        "WORK-02 v2configlab_ DE",
        "WORK-03 oneclickvpnkeys US 7975",
        "WORK-04 42 oneclickvpnkeys",
        "WORK-05 35 oneclickvpnkeys",
        "WORK-06 Fast Deploy Your Own Worker For Creation Of Configs https telegraph.rayan.dpdns",
        "WORK-07 https telegraph.rayan-config.workers.dev persian",
        "WORK-08 https telegraph.rayan-config.workers.dev persian 9713",
        "WORK-09 Fast Deploy Your Own Worker For Creation Of Configs https telegraph.rayan-config 6105",
        "WORK-11 HiByeVPNN",
        "WORK-12 telegram tajrobe_wiki",
        "WORK-13 configV2rayNG FR",
        "WORK-14 V2rayNG3 FR",
        "WORK-15 LINK 10.lowh.net",
        "chillguy_vpn",
        "config_free2 7235",
        "https telegraph.rayan-config.workers.dev persian",
        "https telegraph.rayan-config.workers.dev persian 9713",
        "oneclickvpnkeys DE 5963",
        "oneclickvpnkeys US 6784",
        "oneclickvpnkeys US 7902",
        "oneclickvpnkeys US 7975",
        "telegram tajrobe_wiki",
        "vpnbaz 9219"
      ],
      "added_groups": [
        "URL-TEST TOP 10 INDONESIA"
      ],
      "removed_groups": [
        "URL-TEST TOP 5 INDONESIA"
      ]
    },
    {
      "path": "output/working.yaml",
      "exists": true,
      "previous_exists": true,
      "changed": true,
      "size": 38475,
      "sha256": "ad51ff8efbcbc8c85f20ada0a0cdc3bc1c850e3aa29fe7e6c2645ad217594e6f",
      "previous_size": 34962,
      "previous_sha256": "371e7fcf099471829e559f531578e72e626bd0b8a25d636304dd3e9ec0d1a6c6",
      "proxy_count": 87,
      "previous_proxy_count": 82,
      "groups_count": 11,
      "previous_groups_count": 11,
      "rules_count": 67,
      "added_proxies": [
        "2 DE av2ngFast",
        "CA 39709 Telegram t.me SOSkeyNET",
        "CA 39768 Telegram t.me SOSkeyNET",
        "CA 39775 Telegram t.me SOSkeyNET",
        "GAME-01 2 DE av2ngFast",
        "GAME-02 CA 39768 Telegram t.me SOSkeyNET",
        "GAME-03 oneclickvpnkeys US 2740",
        "GAME-04 oneclickvpnkeys US 5770",
        "GAME-05 oneclickvpnkeys US 6157",
        "GAME-06 oneclickvpnkeys US 4616",
        "GAME-07 CA 39709 Telegram t.me SOSkeyNET",
        "GAME-08 CA 39775 Telegram t.me SOSkeyNET",
        "GAME-09 35 oneclickvpnkeys",
        "GAME-10 CF20",
        "GEN-01 2 DE av2ngFast",
        "GEN-02 CA 39768 Telegram t.me SOSkeyNET",
        "GEN-03 oneclickvpnkeys US 2740",
        "GEN-04 oneclickvpnkeys US 5770",
        "GEN-05 oneclickvpnkeys US 6157",
        "GEN-06 oneclickvpnkeys US 4616",
        "GEN-07 CA 39709 Telegram t.me SOSkeyNET",
        "GEN-08 CA 39775 Telegram t.me SOSkeyNET",
        "GEN-09 35 oneclickvpnkeys",
        "GEN-10 CF20",
        "ID-01 2 DE av2ngFast",
        "ID-02 CA 39768 Telegram t.me SOSkeyNET",
        "ID-03 oneclickvpnkeys US 2740",
        "ID-04 oneclickvpnkeys US 5770",
        "ID-05 oneclickvpnkeys US 6157",
        "ID-06 oneclickvpnkeys US 4616",
        "ID-07 CA 39709 Telegram t.me SOSkeyNET",
        "ID-08 CA 39775 Telegram t.me SOSkeyNET",
        "ID-09 35 oneclickvpnkeys",
        "ID-10 CF20",
        "ID-11 LINK bel432 xl",
        "SOCIAL-01 2 DE av2ngFast",
        "SOCIAL-02 CA 39768 Telegram t.me SOSkeyNET",
        "SOCIAL-03 oneclickvpnkeys US 2740",
        "SOCIAL-04 oneclickvpnkeys US 5770",
        "SOCIAL-05 oneclickvpnkeys US 6157",
        "SOCIAL-06 oneclickvpnkeys US 4616",
        "SOCIAL-07 CA 39709 Telegram t.me SOSkeyNET",
        "SOCIAL-08 CA 39775 Telegram t.me SOSkeyNET",
        "SOCIAL-09 35 oneclickvpnkeys",
        "SOCIAL-10 CF20",
        "STREAM-01 2 DE av2ngFast",
        "STREAM-02 CA 39768 Telegram t.me SOSkeyNET",
        "STREAM-03 oneclickvpnkeys US 2740",
        "STREAM-04 oneclickvpnkeys US 5770",
        "STREAM-05 oneclickvpnkeys US 6157",
        "STREAM-06 oneclickvpnkeys US 4616",
        "STREAM-07 CA 39709 Telegram t.me SOSkeyNET",
        "STREAM-08 CA 39775 Telegram t.me SOSkeyNET",
        "STREAM-09 35 oneclickvpnkeys",
        "STREAM-10 CF20",
        "WORK-01 2 DE av2ngFast",
        "WORK-02 CA 39768 Telegram t.me SOSkeyNET",
        "WORK-03 oneclickvpnkeys US 2740",
        "WORK-04 oneclickvpnkeys US 5770",
        "WORK-05 oneclickvpnkeys US 6157",
        "WORK-06 oneclickvpnkeys US 4616",
        "WORK-07 CA 39709 Telegram t.me SOSkeyNET",
        "WORK-08 CA 39775 Telegram t.me SOSkeyNET",
        "WORK-09 35 oneclickvpnkeys",
        "WORK-10 CF20",
        "oneclickvpnkeys US 2740",
        "oneclickvpnkeys US 4616",
        "oneclickvpnkeys US 5770",
        "oneclickvpnkeys US 6157"
      ],
      "removed_proxies": [
        "27 oneclickvpnkeys",
        "42 oneclickvpnkeys",
        "GAME-01 27 oneclickvpnkeys",
        "GAME-02 v2configlab_ DE",
        "GAME-03 oneclickvpnkeys US 7975",
        "GAME-04 42 oneclickvpnkeys",
        "GAME-05 35 oneclickvpnkeys",
        "GAME-06 CF20",
        "GAME-07 HiByeVPNN",
        "GAME-08 telegram tajrobe_wiki",
        "GAME-09 configV2rayNG FR",
        "GAME-10 V2rayNG3 FR",
        "GEN-01 27 oneclickvpnkeys",
        "GEN-02 v2configlab_ DE",
        "GEN-03 oneclickvpnkeys US 7975",
        "GEN-04 42 oneclickvpnkeys",
        "GEN-05 35 oneclickvpnkeys",
        "GEN-06 CF20",
        "GEN-07 HiByeVPNN",
        "GEN-08 telegram tajrobe_wiki",
        "GEN-09 configV2rayNG FR",
        "GEN-10 V2rayNG3 FR",
        "HiByeVPNN",
        "ID-01 27 oneclickvpnkeys",
        "ID-02 v2configlab_ DE",
        "ID-03 oneclickvpnkeys US 7975",
        "ID-04 42 oneclickvpnkeys",
        "ID-05 35 oneclickvpnkeys",
        "ID-06 LINK bel432 xl",
        "SOCIAL-01 27 oneclickvpnkeys",
        "SOCIAL-02 v2configlab_ DE",
        "SOCIAL-03 oneclickvpnkeys US 7975",
        "SOCIAL-04 42 oneclickvpnkeys",
        "SOCIAL-05 35 oneclickvpnkeys",
        "SOCIAL-06 CF20",
        "SOCIAL-07 HiByeVPNN",
        "SOCIAL-08 telegram tajrobe_wiki",
        "SOCIAL-09 configV2rayNG FR",
        "SOCIAL-10 V2rayNG3 FR",
        "STREAM-01 27 oneclickvpnkeys",
        "STREAM-02 v2configlab_ DE",
        "STREAM-03 oneclickvpnkeys US 7975",
        "STREAM-04 42 oneclickvpnkeys",
        "STREAM-05 35 oneclickvpnkeys",
        "STREAM-06 CF20",
        "STREAM-07 HiByeVPNN",
        "STREAM-08 telegram tajrobe_wiki",
        "STREAM-09 configV2rayNG FR",
        "STREAM-10 V2rayNG3 FR",
        "V2rayNG3 FR",
        "WORK-01 27 oneclickvpnkeys",
        "WORK-02 v2configlab_ DE",
        "WORK-03 oneclickvpnkeys US 7975",
        "WORK-04 42 oneclickvpnkeys",
        "WORK-05 35 oneclickvpnkeys",
        "WORK-06 CF20",
        "WORK-07 HiByeVPNN",
        "WORK-08 telegram tajrobe_wiki",
        "WORK-09 configV2rayNG FR",
        "WORK-10 V2rayNG3 FR",
        "configV2rayNG FR",
        "oneclickvpnkeys US 7975",
        "telegram tajrobe_wiki",
        "v2configlab_ DE"
      ],
      "added_groups": [],
      "removed_groups": []
    }
  ]
}