{
  "file": "output/fast.yaml",
  "proxy_count": 15,
  "best_country_count": 5,
  "responsive_count": 15,
  "fast_max_total": 20,
  "responsive_top_n": 15,
  "responsive_max_avg_delay_ms": 8000,
  "responsive_max_jitter_ms": 5000,
  "responsive_min_success_rate": 0.5,
  "combined_group_max": 30,
  "fallback_group": "FALLBACK CEPAT",
  "names": [
    "hi_proxy_iran 4823",
    "oneclickvpnkeys JP",
    "16 oneclickvpnkeys",
    "oneclickvpnkeys US 6681",
    "oneclickvpnkeys US 1047",
    "GozargahAzad HK",
    "chillguy_vpn",
    "oneclickvpnkeys US 4363",
    "Daily_Configs 7345",
    "oneclickvpnkeys US 5645",
    "hopev2ray 5266",
    "kurdconfig",
    "oneclickvpnkeys US 5649",
    "configV2rayNG US 7659",
    "v2rayNG_Matsuri GB"
  ]
}