{
  "file": "output/fast.yaml",
  "proxy_count": 15,
  "best_country_count": 5,
  "responsive_count": 15,
  "fast_max_total": 20,
  "responsive_top_n": 15,
  "responsive_max_avg_delay_ms": 8000,
  "responsive_max_jitter_ms": 5000,
  "responsive_min_success_rate": 0.5,
  "combined_group_max": 30,
  "fallback_group": "FALLBACK CEPAT",
  "names": [
    "CA 34737 Telegram t.me SOSkeyNET",
    "9https t.me VIPV2rayNGNP",
    "CA 34736 Telegram t.me SOSkeyNET",
    "v2con",
    "oneclickvpnkeys US 3389",
    "GozargahAzad US 3435",
    "filembad 4398",
    "43 oneclickvpnkeys",
    "30 oneclickvpnkeys 8040",
    "hi_proxy_iran 2441",
    "55 oneclickvpnkeys",
    "outline_ir",
    "v2configlab_ DE",
    "GozargahAzad US",
    "outline_vpn FR"
  ]
}